include/defines.vh

`define DATA_WIDTH 32
`define ADDR_WIDTH 11  


// Immediate Src
`define Imm_I 3'b000 
`define Imm_S 3'b001 
`define Imm_B 3'b010 
`define Imm_U 3'b011 
`define Imm_J 3'b100 

// ALU Operations
`define ALU_ADD 4'b0000
`define ALU_SUB 4'b0001
`define ALU_SLL 4'b0010
`define ALU_SLT 4'b0011
`define ALU_SLTU 4'b0100
`define ALU_XOR 4'b0101
`define ALU_SRL 4'b0110
`define ALU_SRA 4'b0111
`define ALU_OR 4'b1000
`define ALU_AND 4'b1001
`define ALU_LUI 4'b1010

// Control Signals
`define OP_RTYPE  7'b0110011
`define OP_ITYPE  7'b0010011
`define OP_LOAD   7'b0000011
`define OP_STORE  7'b0100011
`define OP_BRANCH 7'b1100011
`define OP_JAL    7'b1101111
`define OP_JALR   7'b1100111
`define OP_LUI    7'b0110111
`define OP_AUIPC  7'b0010111

src/alu.v
`timescale 1ns / 1ps
`include "include/defines.vh"

module alu (
    input  wire [31:0] operand_a,
    input  wire [31:0] operand_b,
    input  wire [ 3:0] alu_control,
    output reg  [31:0] alu_result,
    output wire        zero
);

  // Zero flag indicates when result is zero
  assign zero = (alu_result == 32'b0);

  always @(*) begin
    case (alu_control)
      `ALU_ADD:  alu_result = operand_a + operand_b;
      `ALU_SUB:  alu_result = operand_a - operand_b;
      `ALU_SLL:  alu_result = operand_a << operand_b[4:0];
      `ALU_SLT:  alu_result = ($signed(operand_a) < $signed(operand_b)) ? 32'd1 : 32'd0;
      `ALU_SLTU: alu_result = (operand_a < operand_b) ? 32'd1 : 32'd0;
      `ALU_XOR:  alu_result = operand_a ^ operand_b;
      `ALU_SRL:  alu_result = operand_a >> operand_b[4:0];
      `ALU_SRA:  alu_result = $signed(operand_a) >>> operand_b[4:0];
      `ALU_OR:   alu_result = operand_a | operand_b;
      `ALU_AND:  alu_result = operand_a & operand_b;
      default:   alu_result = 32'd0;
    endcase
  end

endmodule

tb/alu_tb.v
`timescale 1ns / 1ps

module alu_tb;
  // Testbench signals
  reg     [31:0] operand_a;
  reg     [31:0] operand_b;
  reg     [ 3:0] alu_control;
  wire    [31:0] alu_result;
  wire           zero;

  // Pass/fail counters
  integer        pass_count = 0;
  integer        fail_count = 0;

  // Instantiate the DUT
  alu uut (
      .operand_a  (operand_a),
      .operand_b  (operand_b),
      .alu_control(alu_control),
      .alu_result (alu_result),
      .zero       (zero)
  );

  // Task to apply a test vector
  task do_test;
    input [31:0] a;
    input [31:0] b;
    input [3:0] ctrl;
    input [31:0] expected;
    begin
      operand_a   = a;
      operand_b   = b;
      alu_control = ctrl;
      #10;
      if (alu_result !== expected) begin
        $display("ERROR: ctrl=%b, a=%d, b=%d => got %d, expected %d", ctrl, a, b, alu_result,
                 expected);
        fail_count = fail_count + 1;
      end else begin
        $display("PASS:  ctrl=%b, a=%d, b=%d => %d", ctrl, a, b, alu_result);
        pass_count = pass_count + 1;
      end
    end
  endtask

  initial begin
    $dumpfile("dump.vcd");
    $dumpvars(0, alu_tb);

    $display("Starting ALU testbench...");

    // ADD
    do_test(32'd15, 32'd10, 4'b0000, 32'd25);
    // SUB
    do_test(32'd15, 32'd10, 4'b0001, 32'd5);
    // SLL (shift left logical)
    do_test(32'h0000_0001, 32'd4, 4'b0010, 32'h0000_0010);
    // SLT (signed)
    do_test(-32'd1, 32'd1, 4'b0011, 32'd1);
    // SLTU (unsigned)
    do_test(32'd1, 32'd2, 4'b0100, 32'd1);
    // XOR
    do_test(32'hF0F0_F0F0, 32'h0F0F_0F0F, 4'b0101, 32'hFFFF_FFFF);
    // SRL (shift right logical)
    do_test(32'h8000_0000, 32'd31, 4'b0110, 32'h0000_0001);
    // SRA (shift right arithmetic)
    do_test(32'h8000_0000, 32'd31, 4'b0111, 32'hFFFF_FFFF);
    // OR
    do_test(32'h1234_5678, 32'h8765_4321, 4'b1000, 32'h9775_5779);
    // AND
    do_test(32'hFFFF_0000, 32'h00FF_FF00, 4'b1001, 32'h00FF_0000);

    // Zero flag check
    operand_a   = 32'd5;
    operand_b   = 32'd5;
    alu_control = 4'b0001;  // SUB
    #10;
    if (zero) begin
      $display("PASS: Zero flag asserted");
      pass_count = pass_count + 1;
    end else begin
      $display("ERROR: Zero flag not asserted");
      fail_count = fail_count + 1;
    end

    $display("ALU testbench complete.");
    $display("Total PASS: %0d", pass_count);
    $display("Total FAIL: %0d", fail_count);
    $finish;
  end
endmodule

waves/alu.vcd
$date
	Fri Jul  4 17:37:28 2025
$end
$version
	Icarus Verilog
$end
$timescale
	1ps
$end
$scope module alu_tb $end
$var wire 1 ! zero $end
$var wire 32 " alu_result [31:0] $end
$var reg 4 # alu_control [3:0] $end
$var reg 32 $ operand_a [31:0] $end
$var reg 32 % operand_b [31:0] $end
$var integer 32 & fail_count [31:0] $end
$var integer 32 ' pass_count [31:0] $end
$scope module uut $end
$var wire 4 ( alu_control [3:0] $end
$var wire 32 ) operand_a [31:0] $end
$var wire 32 * operand_b [31:0] $end
$var wire 1 ! zero $end
$var parameter 4 + ALU_ADD $end
$var parameter 4 , ALU_AND $end
$var parameter 4 - ALU_OR $end
$var parameter 4 . ALU_SLL $end
$var parameter 4 / ALU_SLT $end
$var parameter 4 0 ALU_SLTU $end
$var parameter 4 1 ALU_SRA $end
$var parameter 4 2 ALU_SRL $end
$var parameter 4 3 ALU_SUB $end
$var parameter 4 4 ALU_XOR $end
$var reg 32 5 alu_result [31:0] $end
$upscope $end
$scope task do_test $end
$var reg 32 6 a [31:0] $end
$var reg 32 7 b [31:0] $end
$var reg 4 8 ctrl [3:0] $end
$var reg 32 9 expected [31:0] $end
$upscope $end
$upscope $end
$enddefinitions $end
$comment Show the parameter values. $end
$dumpall
b101 4
b1 3
b110 2
b111 1
b100 0
b11 /
b10 .
b1000 -
b1001 ,
b0 +
$end
#0
$dumpvars
b11001 9
b0 8
b1010 7
b1111 6
b11001 5
b1010 *
b1111 )
b0 (
b0 '
b0 &
b1010 %
b1111 $
b0 #
b11001 "
0!
$end
#10000
b101 "
b101 5
b1 #
b1 (
b101 9
b1 8
b1 '
#20000
b10000 "
b10000 5
b10 #
b10 (
b100 %
b100 *
b1 $
b1 )
b10000 9
b10 8
b100 7
b1 6
b10 '
#30000
b1 "
b1 5
b11 #
b11 (
b1 %
b1 *
b11111111111111111111111111111111 $
b11111111111111111111111111111111 )
b1 9
b11 8
b1 7
b11111111111111111111111111111111 6
b11 '
#40000
b100 #
b100 (
b10 %
b10 *
b1 $
b1 )
b100 8
b10 7
b1 6
b100 '
#50000
b11111111111111111111111111111111 "
b11111111111111111111111111111111 5
b101 #
b101 (
b1111000011110000111100001111 %
b1111000011110000111100001111 *
b11110000111100001111000011110000 $
b11110000111100001111000011110000 )
b11111111111111111111111111111111 9
b101 8
b1111000011110000111100001111 7
b11110000111100001111000011110000 6
b101 '
#60000
b1 "
b1 5
b110 #
b110 (
b11111 %
b11111 *
b10000000000000000000000000000000 $
b10000000000000000000000000000000 )
b1 9
b110 8
b11111 7
b10000000000000000000000000000000 6
b110 '
#70000
b11111111111111111111111111111111 "
b11111111111111111111111111111111 5
b111 #
b111 (
b11111111111111111111111111111111 9
b111 8
b111 '
#80000
b10010111011101010101011101111001 "
b10010111011101010101011101111001 5
b1000 #
b1000 (
b10000111011001010100001100100001 %
b10000111011001010100001100100001 *
b10010001101000101011001111000 $
b10010001101000101011001111000 )
b10010111011101010101011101111001 9
b1000 8
b10000111011001010100001100100001 7
b10010001101000101011001111000 6
b1000 '
#90000
b111111110000000000000000 "
b111111110000000000000000 5
b1001 #
b1001 (
b111111111111111100000000 %
b111111111111111100000000 *
b11111111111111110000000000000000 $
b11111111111111110000000000000000 )
b111111110000000000000000 9
b1001 8
b111111111111111100000000 7
b11111111111111110000000000000000 6
b1001 '
#100000
1!
b0 "
b0 5
b1 #
b1 (
b101 %
b101 *
b101 $
b101 )
b1010 '
#110000
b1011 '
