src/alu_control.v
module alu_control(
  input  wire [1:0] ALUOp,
  input  wire [2:0] funct3,
  input  wire       funct7_5,
  output reg  [3:0] ALUCtrl
);

  always @(*) begin
    case (ALUOp)
      2'b00: ALUCtrl = ALU_ADD;
      2'b01: ALUCtrl = ALU_SUB;
      2'b11: ALUCtrl = ALU_ADD;  // LUI: pass immediate upper bits
      2'b10: begin
        case ({funct7_5, funct3})
          4'b0_000: ALUCtrl = ALU_ADD;
          4'b1_000: ALUCtrl = ALU_SUB;
          4'b0_001: ALUCtrl = ALU_SLL;
          4'b0_010: ALUCtrl = ALU_SLT;
          4'b0_011: ALUCtrl = ALU_SLTU;
          4'b0_100: ALUCtrl = ALU_XOR;
          4'b0_101: ALUCtrl = ALU_SRL;
          4'b1_101: ALUCtrl = ALU_SRA;
          4'b0_110: ALUCtrl = ALU_OR;
          4'b0_111: ALUCtrl = ALU_AND;
          default:  ALUCtrl = ALU_ADD;
        endcase
      end
    endcase
  end
endmodule

tb/alu_control_tb.v
module alu_control_tb;

  reg [1:0] ALUOp;
  reg [2:0] funct3;
  reg funct7_5;
  wire [3:0] ALUCtrl;

  alu_control uut (
      .ALUOp(ALUOp),
      .funct3(funct3),
      .funct7_5(funct7_5),
      .ALUCtrl(ALUCtrl)
  );

  // ALU Control Signals
  localparam ALU_ADD = 4'b0000;
  localparam ALU_SUB = 4'b0001;
  localparam ALU_SLL = 4'b0010;
  localparam ALU_SLT = 4'b0011;
  localparam ALU_SLTU = 4'b0100;
  localparam ALU_XOR = 4'b0101;
  localparam ALU_SRL = 4'b0110;
  localparam ALU_SRA = 4'b0111;
  localparam ALU_OR = 4'b1000;
  localparam ALU_AND = 4'b1001;
  localparam ALU_LUI = 4'b1010;

  integer failed, passed;

  task check_output(input [3:0] expected, input [3:0] actual, input string test_name);
    if (actual !== expected) begin
      $display("%s failed: expected %b, got %b", test_name, expected, actual);
      failed = failed + 1;
    end else begin
      $display("%s passed: got %b", test_name, actual);
      passed = passed + 1;
    end
  endtask


  initial begin
    // dump waveform
    $dumpfile("dump.vcd");
    $dumpvars(0, alu_control_tb);

    passed = 0;
    failed = 0;


    // Test cases
    $display("\n--- ALU Control Testbench Start ---\n");

    // Test case 1: ALUOp = 00 (ADD)
    ALUOp = 2'b00;
    funct3 = 3'b101;
    funct7_5 = 1;
    #1;
    check_output(ALU_ADD, ALUCtrl, "Test Case 1");

    // Test case 2: ALUOp = 01 (SUB)
    ALUOp = 2'b01;
    funct3 = 3'b010;
    funct7_5 = 1;
    #1;
    check_output(ALU_SUB, ALUCtrl, "Test Case 2");

    // Test case 3: ALUOp = 10, funct3 = 000, funct7_5 = 0 (ADD)
    ALUOp = 2'b10;
    funct3 = 3'b000;
    funct7_5 = 0;
    #1;
    check_output(ALU_ADD, ALUCtrl, "Test Case 3");

    // Test case 4: ALUOp = 10, funct3 = 000, funct7_5 = 1 (SUB)
    ALUOp = 2'b10;
    funct3 = 3'b000;
    funct7_5 = 1;
    #1;
    check_output(ALU_SUB, ALUCtrl, "Test Case 4");

    // Test case 5: ALUOp = 10, funct3 = 001, funct7_5 = 0 (SLL)
    ALUOp = 2'b10;
    funct3 = 3'b001;
    funct7_5 = 0;
    #1;
    check_output(ALU_SLL, ALUCtrl, "Test Case 5");

    // Test case 6: ALUOp = 10, funct3 = 010, funct7_5 = 0 (SLT)
    ALUOp = 2'b10;
    funct3 = 3'b010;
    funct7_5 = 0;
    #1;
    check_output(ALU_SLT, ALUCtrl, "Test Case 6");

    // Test case 7: ALUOp = 10, funct3 = 011, funct7_5 = 0 (SLTU)
    ALUOp = 2'b10;
    funct3 = 3'b011;
    funct7_5 = 0;
    #1;
    check_output(ALU_SLTU, ALUCtrl, "Test Case 7");

    // Test case 8: ALUOp = 10, funct3 = 100, funct7_5 = 0 (XOR)
    ALUOp = 2'b10;
    funct3 = 3'b100;
    funct7_5 = 0;
    #1;
    check_output(ALU_XOR, ALUCtrl, "Test Case 8");

    // Test case 9: ALUOp = 10, funct3 = 101, funct7_5 = 0 (SRL)
    ALUOp = 2'b10;
    funct3 = 3'b101;
    funct7_5 = 0;
    #1;
    check_output(ALU_SRL, ALUCtrl, "Test Case 9");

    // Test case 10: ALUOp = 10, funct3 = 101, funct7_5 = 1 (SRA)
    ALUOp = 2'b10;
    funct3 = 3'b101;
    funct7_5 = 1;
    #1;
    check_output(ALU_SRA, ALUCtrl, "Test Case 10");

    // Test case 11: ALUOp = 10, funct3 = 110, funct7_5 = 0 (OR)
    ALUOp = 2'b10;
    funct3 = 3'b110;
    funct7_5 = 0;
    #1;
    check_output(ALU_OR, ALUCtrl, "Test Case 11");

    // Test case 12: ALUOp = 10, funct3 = 111, funct7_5 = 0 (AND)
    ALUOp = 2'b10;
    funct3 = 3'b111;
    funct7_5 = 0;
    #1;
    check_output(ALU_AND, ALUCtrl, "Test Case 12");

    // Test case 13: ALUOp = 11 (LUI)
    ALUOp = 2'b11;
    funct3 = 3'b000;
    funct7_5 = 0;
    #1;
    check_output(ALU_LUI, ALUCtrl, "Test Case 13");

    $display("\n--- ALU Control Testbench End ---\n");
    $display("Total Tests Passed: %d", passed);
    $display("Total Tests Failed: %d", failed);

  end

endmodule

waves/alu_control.vcd
$date
	Sat Jul  5 19:31:05 2025
$end
$version
	Icarus Verilog
$end
$timescale
	1s
$end
$scope module alu_control_tb $end
$var wire 4 ! ALUCtrl [3:0] $end
$var parameter 4 " ALU_ADD $end
$var parameter 4 # ALU_AND $end
$var parameter 4 $ ALU_LUI $end
$var parameter 4 % ALU_OR $end
$var parameter 4 & ALU_SLL $end
$var parameter 4 ' ALU_SLT $end
$var parameter 4 ( ALU_SLTU $end
$var parameter 4 ) ALU_SRA $end
$var parameter 4 * ALU_SRL $end
$var parameter 4 + ALU_SUB $end
$var parameter 4 , ALU_XOR $end
$var reg 2 - ALUOp [1:0] $end
$var reg 3 . funct3 [2:0] $end
$var reg 1 / funct7_5 $end
$var integer 32 0 failed [31:0] $end
$var integer 32 1 passed [31:0] $end
$scope module uut $end
$var wire 2 2 ALUOp [1:0] $end
$var wire 3 3 funct3 [2:0] $end
$var wire 1 / funct7_5 $end
$var reg 4 4 ALUCtrl [3:0] $end
$upscope $end
$scope task check_output $end
$var reg 4 5 actual [3:0] $end
$var reg 4 6 expected [3:0] $end
$upscope $end
$upscope $end
$enddefinitions $end
$comment Show the parameter values. $end
$dumpall
b101 ,
b1 +
b110 *
b111 )
b100 (
b11 '
b10 &
b1000 %
b1010 $
b1001 #
b0 "
$end
#0
$dumpvars
bx 6
bx 5
b0 4
b101 3
b0 2
b0 1
b0 0
1/
b101 .
b0 -
b0 !
$end
#1
b1 !
b1 4
b10 .
b10 3
b1 -
b1 2
b1 1
b0 5
b0 6
#2
b0 !
b0 4
0/
b0 .
b0 3
b10 -
b10 2
b10 1
b1 5
b1 6
#3
b1 !
b1 4
1/
b11 1
b0 5
b0 6
#4
b10 !
b10 4
0/
b1 .
b1 3
b100 1
b1 5
b1 6
#5
b11 !
b11 4
b10 .
b10 3
b101 1
b10 5
b10 6
#6
b100 !
b100 4
b11 .
b11 3
b110 1
b11 5
b11 6
#7
b101 !
b101 4
b100 .
b100 3
b111 1
b100 5
b100 6
#8
b110 !
b110 4
b101 .
b101 3
b1000 1
b101 5
b101 6
#9
b111 !
b111 4
1/
b1001 1
b110 5
b110 6
#10
b1000 !
b1000 4
0/
b110 .
b110 3
b1010 1
b111 5
b111 6
#11
b1001 !
b1001 4
b111 .
b111 3
b1011 1
b1000 5
b1000 6
#12
b1010 !
b1010 4
b0 .
b0 3
b11 -
b11 2
b1100 1
b1001 5
b1001 6
#13
b1101 1
b1010 5
b1010 6
