include/defines.vh
`define DATA_WIDTH 32
`define ADDR_WIDTH 11  

// Immediate Src
`define Imm_I 3'b000 
`define Imm_S 3'b001 
`define Imm_B 3'b010 
`define Imm_U 3'b011 
`define Imm_J 3'b100 
`define Imm_NONE 3'b111

// ALU Operations
`define ALU_ADD 4'b0000
`define ALU_SUB 4'b0001
`define ALU_SLL 4'b0010
`define ALU_SLT 4'b0011
`define ALU_SLTU 4'b0100
`define ALU_XOR 4'b0101
`define ALU_SRL 4'b0110
`define ALU_SRA 4'b0111
`define ALU_OR 4'b1000
`define ALU_AND 4'b1001
`define ALU_LUI 4'b1010

// Control Signals
`define OP_RTYPE 7'b0110011
`define OP_ITYPE 7'b0010011
`define OP_LOAD 7'b0000011
`define OP_STORE 7'b0100011
`define OP_BRANCH 7'b1100011
`define OP_JAL 7'b1101111
`define OP_JALR 7'b1100111
`define OP_LUI 7'b0110111
`define OP_AUIPC 7'b0010111
`define OP_SYSTEM 7'b1110011

src/leaf/alu_control.v
`timescale 1ps / 1ps
`include "defines.vh"

module alu_control (
    input  wire [1:0] alu_op,
    input  wire [2:0] funct3,
    input  wire       funct7_5,
    output reg  [3:0] alu_ctrl
);

  // ALU Control Signals


  always @(*) begin
    case (alu_op)
      2'b00: alu_ctrl = `ALU_ADD;
      2'b01: alu_ctrl = `ALU_SUB;
      2'b11: alu_ctrl = `ALU_LUI;
      2'b10: begin
        case ({
          funct7_5, funct3
        })
          4'b0_000: alu_ctrl = `ALU_ADD;
          4'b1_000: alu_ctrl = `ALU_SUB;
          4'b0_001: alu_ctrl = `ALU_SLL;
          4'b0_010: alu_ctrl = `ALU_SLT;
          4'b0_011: alu_ctrl = `ALU_SLTU;
          4'b0_100: alu_ctrl = `ALU_XOR;
          4'b0_101: alu_ctrl = `ALU_SRL;
          4'b1_101: alu_ctrl = `ALU_SRA;
          4'b0_110: alu_ctrl = `ALU_OR;
          4'b0_111: alu_ctrl = `ALU_AND;
          default:  alu_ctrl = `ALU_ADD;
        endcase
      end
    endcase
  end
endmodule

tb/alu_control_tb.v
`timescale 1ns / 1ps
module alu_control_tb;

  reg [1:0] ALUOp;
  reg [2:0] funct3;
  reg funct7_5;
  wire [3:0] ALUCtrl;

  alu_control uut (
      .alu_op  (ALUOp),
      .funct3  (funct3),
      .funct7_5(funct7_5),
      .alu_ctrl(ALUCtrl)
  );

  // ALU Control Signals
  localparam ALU_ADD = 4'b0000;
  localparam ALU_SUB = 4'b0001;
  localparam ALU_SLL = 4'b0010;
  localparam ALU_SLT = 4'b0011;
  localparam ALU_SLTU = 4'b0100;
  localparam ALU_XOR = 4'b0101;
  localparam ALU_SRL = 4'b0110;
  localparam ALU_SRA = 4'b0111;
  localparam ALU_OR = 4'b1000;
  localparam ALU_AND = 4'b1001;
  localparam ALU_LUI = 4'b1010;

  integer failed, passed;

  task check_output(input [3:0] expected, input [3:0] actual, input string test_name);
    if (actual !== expected) begin
      $display("%s failed: expected %b, got %b", test_name, expected, actual);
      failed = failed + 1;
    end else begin
      $display("%s passed: got %b", test_name, actual);
      passed = passed + 1;
    end
  endtask


  initial begin
    // dump waveform
    $dumpfile("dump.vcd");
    $dumpvars(0, alu_control_tb);

    passed = 0;
    failed = 0;


    // Test cases
    $display("\n--- ALU Control Testbench Start ---\n");

    // Test case 1: ALUOp = 00 (ADD)
    ALUOp = 2'b00;
    funct3 = 3'b101;
    funct7_5 = 1;
    #1;
    check_output(ALU_ADD, ALUCtrl, "Test Case 1");

    // Test case 2: ALUOp = 01 (SUB)
    ALUOp = 2'b01;
    funct3 = 3'b010;
    funct7_5 = 1;
    #1;
    check_output(ALU_SUB, ALUCtrl, "Test Case 2");

    // Test case 3: ALUOp = 10, funct3 = 000, funct7_5 = 0 (ADD)
    ALUOp = 2'b10;
    funct3 = 3'b000;
    funct7_5 = 0;
    #1;
    check_output(ALU_ADD, ALUCtrl, "Test Case 3");

    // Test case 4: ALUOp = 10, funct3 = 000, funct7_5 = 1 (SUB)
    ALUOp = 2'b10;
    funct3 = 3'b000;
    funct7_5 = 1;
    #1;
    check_output(ALU_SUB, ALUCtrl, "Test Case 4");

    // Test case 5: ALUOp = 10, funct3 = 001, funct7_5 = 0 (SLL)
    ALUOp = 2'b10;
    funct3 = 3'b001;
    funct7_5 = 0;
    #1;
    check_output(ALU_SLL, ALUCtrl, "Test Case 5");

    // Test case 6: ALUOp = 10, funct3 = 010, funct7_5 = 0 (SLT)
    ALUOp = 2'b10;
    funct3 = 3'b010;
    funct7_5 = 0;
    #1;
    check_output(ALU_SLT, ALUCtrl, "Test Case 6");

    // Test case 7: ALUOp = 10, funct3 = 011, funct7_5 = 0 (SLTU)
    ALUOp = 2'b10;
    funct3 = 3'b011;
    funct7_5 = 0;
    #1;
    check_output(ALU_SLTU, ALUCtrl, "Test Case 7");

    // Test case 8: ALUOp = 10, funct3 = 100, funct7_5 = 0 (XOR)
    ALUOp = 2'b10;
    funct3 = 3'b100;
    funct7_5 = 0;
    #1;
    check_output(ALU_XOR, ALUCtrl, "Test Case 8");

    // Test case 9: ALUOp = 10, funct3 = 101, funct7_5 = 0 (SRL)
    ALUOp = 2'b10;
    funct3 = 3'b101;
    funct7_5 = 0;
    #1;
    check_output(ALU_SRL, ALUCtrl, "Test Case 9");

    // Test case 10: ALUOp = 10, funct3 = 101, funct7_5 = 1 (SRA)
    ALUOp = 2'b10;
    funct3 = 3'b101;
    funct7_5 = 1;
    #1;
    check_output(ALU_SRA, ALUCtrl, "Test Case 10");

    // Test case 11: ALUOp = 10, funct3 = 110, funct7_5 = 0 (OR)
    ALUOp = 2'b10;
    funct3 = 3'b110;
    funct7_5 = 0;
    #1;
    check_output(ALU_OR, ALUCtrl, "Test Case 11");

    // Test case 12: ALUOp = 10, funct3 = 111, funct7_5 = 0 (AND)
    ALUOp = 2'b10;
    funct3 = 3'b111;
    funct7_5 = 0;
    #1;
    check_output(ALU_AND, ALUCtrl, "Test Case 12");

    // Test case 13: ALUOp = 11 (LUI)
    ALUOp = 2'b11;
    funct3 = 3'b000;
    funct7_5 = 0;
    #1;
    check_output(ALU_LUI, ALUCtrl, "Test Case 13");

    $display("\n--- ALU Control Testbench End ---\n");
    $display("Total Tests Passed: %d", passed);
    $display("Total Tests Failed: %d", failed);

  end

endmodule

waves/alu_control.vcd
$date
	Tue Aug 26 21:19:24 2025
$end
$version
	Icarus Verilog
$end
$timescale
	1ps
$end
$scope module alu_control_tb $end
$var wire 4 ! ALUCtrl [3:0] $end
$var parameter 4 " ALU_ADD $end
$var parameter 4 # ALU_AND $end
$var parameter 4 $ ALU_OR $end
$var parameter 4 % ALU_SLL $end
$var parameter 4 & ALU_SLT $end
$var parameter 4 ' ALU_SLTU $end
$var parameter 4 ( ALU_SRA $end
$var parameter 4 ) ALU_SRL $end
$var parameter 4 * ALU_SUB $end
$var parameter 4 + ALU_XOR $end
$var reg 2 , ALUOp [1:0] $end
$var reg 3 - funct3 [2:0] $end
$var reg 1 . funct7_5 $end
$var integer 32 / failed [31:0] $end
$var integer 32 0 passed [31:0] $end
$scope module uut $end
$var wire 2 1 alu_op [1:0] $end
$var wire 3 2 funct3 [2:0] $end
$var wire 1 . funct7_5 $end
$var reg 4 3 alu_ctrl [3:0] $end
$upscope $end
$scope task check_output $end
$var reg 4 4 actual [3:0] $end
$var reg 4 5 expected [3:0] $end
$var reg 256 6 test_name [255:0] $end
$upscope $end
$upscope $end
$enddefinitions $end
$comment Show the parameter values. $end
$dumpall
b101 +
b1 *
b110 )
b111 (
b100 '
b11 &
b10 %
b1000 $
b1001 #
b0 "
$end
#0
$dumpvars
bx 6
bx 5
bx 4
b0 3
b101 2
b0 1
b0 0
b0 /
1.
b101 -
b0 ,
b0 !
$end
#1000
b1 !
b1 3
b10 -
b10 2
b1 ,
b1 1
b1 0
b1010100011001010111001101110100001000000011000100111010001000000100000101001100010101010100111101110000001100000011000000100000001011010011111000100000010000010100010001000100 6
b0 4
b0 5
#2000
b0 !
b0 3
0.
b0 -
b0 2
b10 ,
b10 1
b10 0
b1010100011001010111001101110100001000000011001000111010001000000100000101001100010101010100111101110000001100000011000100100000001011010011111000100000010100110101010101000010 6
b1 4
b1 5
#3000
b1 !
b1 3
1.
b11 0
b1010100011001010111001101110100001000000011001100111010001000000100111101110000001100010011000000100000011001100011001100111101001100000011000000110000001000000110011000110111001111010011000000100000001011010011111000100000010000010100010001000100 6
b0 4
b0 5
#4000
b10 !
b10 3
0.
b1 -
b1 2
b100 0
b1010100011001010111001101110100001000000011010000111010001000000100111101110000001100010011000000100000011001100011001100111101001100000011000000110000001000000110011000110111001111010011000100100000001011010011111000100000010100110101010101000010 6
b1 4
b1 5
#5000
b11 !
b11 3
b10 -
b10 2
b101 0
b101010001100101011100110111010000100000001101010011101000100000010100110100110001001100 6
b10 4
b10 5
#6000
b100 !
b100 3
b11 -
b11 2
b110 0
b101010001100101011100110111010000100000001101100011101000100000010100110100110001010100 6
b11 4
b11 5
#7000
b101 !
b101 3
b100 -
b100 2
b111 0
b10101000110010101110011011101000010000000110111001110100010000001010011010011000101010001010101 6
b100 4
b100 5
#8000
b110 !
b110 3
b101 -
b101 2
b1000 0
b101010001100101011100110111010000100000001110000011101000100000010110000100111101010010 6
b101 4
b101 5
#9000
b111 !
b111 3
1.
b1001 0
b101010001100101011100110111010000100000001110010011101000100000010100110101001001001100 6
b110 4
b110 5
#10000
b1000 !
b1000 3
0.
b110 -
b110 2
b1010 0
b10101000110010101110011011101000010000000110001001100000011101000100000010100110101001001000001 6
b111 4
b111 5
#11000
b1001 !
b1001 3
b111 -
b111 2
b1011 0
b101010001100101011100110111010000100000001100010011000100111010001000000100111101010010 6
b1000 4
b1000 5
#12000
b0 !
b0 3
b0 -
b0 2
b11 ,
b11 1
b1100 0
b10101000110010101110011011101000010000000110001001100100011101000100000010000010100111001000100 6
b1001 4
b1001 5
#13000
b0 ,
b0 1
b1101 0
b10101000110010101110011011101000010000000110001001100110011101000100000010011000101010101001001 6
b0 4
b0 5
#14000
b1001 !
b1001 3
b111 -
b111 2
b10 ,
b10 1
b1110 0
b10101000110010101110011011101000010000000110001001101000011101000100000010000010100010001000100010010010010000000101000010000010100110001010101010011110111000000111101001100000011000000101001 6
#15000
b1000 !
b1000 3
b110 -
b110 2
b1111 0
b1010100011001010111001101110100001000000011000100110101001110100010000001000001010011100100010001001001 6
b1001 4
b1001 5
#16000
b101 !
b101 3
b100 -
b100 2
b10000 0
b10101000110010101110011011101000010000000110001001101100011101000100000010011110101001001001001 6
b1000 4
b1000 5
#17000
b11 !
b11 3
b10 -
b10 2
b10001 0
b1010100011001010111001101110100001000000011000100110111001110100010000001011000010011110101001001001001 6
b101 4
b101 5
#18000
b100 !
b100 3
b11 -
b11 2
b10010 0
b1010100011001010111001101110100001000000011000100111000001110100010000001010011010011000101010001001001 6
b11 4
b11 5
#19000
b10 !
b10 3
b1 -
b1 2
b10011 0
b101010001100101011100110111010000100000001100010011100100111010001000000101001101001100010101000100100101010101 6
b100 4
b100 5
#20000
b110 !
b110 3
b101 -
b101 2
b10100 0
b1010100011001010111001101110100001000000011001000110000001110100010000001010011010011000100110001001001 6
b10 4
b10 5
#21000
b111 !
b111 3
1.
b10101 0
b1010100011001010111001101110100001000000011001000110001001110100010000001010011010100100100110001001001 6
b110 4
b110 5
#22000
b10110 0
b1010100011001010111001101110100001000000011001000110010001110100010000001010011010100100100000101001001 6
b111 4
b111 5
