include/defines.vh
`define DATA_WIDTH 32
`define ADDR_WIDTH 11  

// Immediate Src
`define Imm_I 3'b000 
`define Imm_S 3'b001 
`define Imm_B 3'b010 
`define Imm_U 3'b011 
`define Imm_J 3'b100 
`define Imm_NONE 3'b111

// ALU Operations
`define ALU_ADD 4'b0000
`define ALU_SUB 4'b0001
`define ALU_SLL 4'b0010
`define ALU_SLT 4'b0011
`define ALU_SLTU 4'b0100
`define ALU_XOR 4'b0101
`define ALU_SRL 4'b0110
`define ALU_SRA 4'b0111
`define ALU_OR 4'b1000
`define ALU_AND 4'b1001
`define ALU_LUI 4'b1010

// Control Signals
`define OP_RTYPE 7'b0110011
`define OP_ITYPE 7'b0010011
`define OP_LOAD 7'b0000011
`define OP_STORE 7'b0100011
`define OP_BRANCH 7'b1100011
`define OP_JAL 7'b1101111
`define OP_JALR 7'b1100111
`define OP_LUI 7'b0110111
`define OP_AUIPC 7'b0010111
`define OP_SYSTEM 7'b1110011

src/leaf/branch_comp.v
`timescale 1ps / 1ps
`include "defines.vh"


module branch_comp (
    input  wire [31:0] op1,
    input  wire [31:0] op2,
    input  wire [ 2:0] funct3,
    output reg         branch_taken
);


  localparam BEQ = 3'b000;  // Branch if equal
  localparam BNE = 3'b001;  // Branch if not equal
  localparam BLT = 3'b100;  // Branch if less than (signed)
  localparam BGE = 3'b101;  // Branch if greater than or equal (signed)
  localparam BLTU = 3'b110;  // Branch if less than (unsigned)
  localparam BGEU = 3'b111;  // Branch if greater than or equal (unsigned)

  always @(*) begin
    case (funct3)
      BEQ: branch_taken = (op1 == op2);
      BNE: branch_taken = (op1 != op2);
      BLT: branch_taken = ($signed(op1) < $signed(op2));
      BGE: branch_taken = ($signed(op1) >= $signed(op2));
      BLTU: branch_taken = (op1 < op2);
      BGEU: branch_taken = (op1 >= op2);
      default: branch_taken = 1'b0;
    endcase
  end

endmodule

tb/branch_comp_tb.v
`timescale 1ps/1ps
module branch_comp_tb;
  reg signed [31:0] op1;
  reg signed [31:0] op2;
  reg  [ 2:0] funct3;
  wire        branch;

  branch_comp uut (
      .op1(op1),
      .op2(op2),
      .funct3(funct3),
      .branch_taken(branch)
  );
  integer failed, passed;

  task check_output(input expected, input actual, input string test_name);
    if (actual !== expected) begin
      $display("%s failed: expected %b, got %b", test_name, expected, actual);
      failed = failed + 1;
    end else begin
      $display("%s passed: got %b", test_name, actual);
      passed = passed + 1;
    end
  endtask

  initial begin
    $dumpfile("dump.vcd");
    $dumpvars(0, branch_comp_tb);

    passed = 0;
    failed = 0;

    $display("\n--- Branch Comparator Testbench Start ---\n");

    op1 = 32'hA5A5A5A5;
    op2 = 32'hA5A5A5A5;
    funct3 = 3'b000;
    #1;
    check_output(1'b1, branch, "BEQ");

    op1 = 32'hA5A5A5A5;
    op2 = 32'hB5B5B5B5;
    funct3 = 3'b000;
    #1;
    check_output(1'b0, branch, "BEQ (Negative)");

    op2 = 32'hB6B6B6B6;
    funct3 = 3'b001;
    #1;
    check_output(1'b1, branch, "BNE");

    op1 = 32'hB6B6B6B6;
    op2 = 32'hB6B6B6B6;
    funct3 = 3'b001;
    #1;
    check_output(1'b0, branch, "BNE (Negative)");


    op1 = -32'd10;
    op2 = -32'd5;
    funct3 = 3'b100;
    #1;
    check_output(1'b1, branch, "BLT");

    op1 = 32'd2;
    op2 = -32'd5;
    funct3 = 3'b100;
    #1;
    check_output(1'b0, branch, "BLT (Negative)");


    op1 = -32'd5;
    op2 = -32'd10;
    funct3 = 3'b101;
    #1;
    check_output(1'b1, branch, "BGE");

    op1 = -32'd20;
    op2 = -32'd10;
    funct3 = 3'b101;
    #1;
    check_output(1'b0, branch, "BGE (Negative)");

    op1 = 32'h00000001;
    op2 = 32'hFFFFFFFF;
    funct3 = 3'b110;
    #1;
    check_output(1'b1, branch, "BLTU");

    op1 = 32'hFFFFFFFF;
    op2 = 32'h00000001;
    funct3 = 3'b110;
    #1;
    check_output(1'b0, branch, "BLTU (Negative)");


    op2 = 32'hFFFFFFFF;
    funct3 = 3'b111;
    #1;
    check_output(1'b1, branch, "BGEU");

    op2 = 32'hFFFFFFFF;
    op1 = 32'h00000001;
    funct3 = 3'b111;
    #1;
    check_output(1'b0, branch, "BGEU (Negative)");

    funct3 = 3'b010;
    #1;
    check_output(1'b0, branch, "No Branch (Default)");

    $display("\n--- Branch Comparator Testbench End ---\n");

    $display("Total Tests: %d, Passed: %d, Failed: %d", passed + failed, passed, failed);

  end



endmodule

waves/branch_comp.vcd
$date
	Tue Aug 26 21:19:24 2025
$end
$version
	Icarus Verilog
$end
$timescale
	1ps
$end
$scope module branch_comp_tb $end
$var wire 1 ! branch $end
$var reg 3 " funct3 [2:0] $end
$var reg 32 # op1 [31:0] $end
$var reg 32 $ op2 [31:0] $end
$var integer 32 % failed [31:0] $end
$var integer 32 & passed [31:0] $end
$scope module uut $end
$var wire 3 ' funct3 [2:0] $end
$var wire 32 ( op1 [31:0] $end
$var wire 32 ) op2 [31:0] $end
$var parameter 3 * BEQ $end
$var parameter 3 + BGE $end
$var parameter 3 , BGEU $end
$var parameter 3 - BLT $end
$var parameter 3 . BLTU $end
$var parameter 3 / BNE $end
$var reg 1 ! branch_taken $end
$upscope $end
$scope task check_output $end
$var reg 1 0 actual $end
$var reg 1 1 expected $end
$var reg 512 2 test_name [511:0] $end
$upscope $end
$upscope $end
$enddefinitions $end
$comment Show the parameter values. $end
$dumpall
b1 /
b110 .
b100 -
b111 ,
b101 +
b0 *
$end
#0
$dumpvars
bx 2
x1
x0
b10100101101001011010010110100101 )
b10100101101001011010010110100101 (
b0 '
b0 &
b0 %
b10100101101001011010010110100101 $
b10100101101001011010010110100101 #
b0 "
1!
$end
#1
0!
b10110101101101011011010110110101 $
b10110101101101011011010110110101 )
b1 &
b10000100100010101010001 2
10
11
#2
1!
b1 "
b1 '
b10110110101101101011011010110110 $
b10110110101101101011011010110110 )
b10 &
b100001001000101010100010010000000101000010011100110010101100111011000010111010001101001011101100110010100101001 2
00
01
#3
0!
b10110110101101101011011010110110 #
b10110110101101101011011010110110 (
b11 &
b10000100100111001000101 2
10
11
#4
1!
b100 "
b100 '
b11111111111111111111111111111011 $
b11111111111111111111111111111011 )
b11111111111111111111111111110110 #
b11111111111111111111111111110110 (
b100 &
b100001001001110010001010010000000101000010011100110010101100111011000010111010001101001011101100110010100101001 2
00
01
#5
0!
b10 #
b10 (
b101 &
b10000100100110001010100 2
10
11
#6
1!
b101 "
b101 '
b11111111111111111111111111110110 $
b11111111111111111111111111110110 )
b11111111111111111111111111111011 #
b11111111111111111111111111111011 (
b110 &
b100001001001100010101000010000000101000010011100110010101100111011000010111010001101001011101100110010100101001 2
00
01
#7
0!
b11111111111111111111111111101100 #
b11111111111111111111111111101100 (
b111 &
b10000100100011101000101 2
10
11
#8
1!
b110 "
b110 '
b11111111111111111111111111111111 $
b11111111111111111111111111111111 )
b1 #
b1 (
b1000 &
b100001001000111010001010010000000101000010011100110010101100111011000010111010001101001011101100110010100101001 2
00
01
#9
0!
b1 $
b1 )
b11111111111111111111111111111111 #
b11111111111111111111111111111111 (
b1001 &
b1000010010011000101010001010101 2
10
11
#10
1!
b111 "
b111 '
b11111111111111111111111111111111 $
b11111111111111111111111111111111 )
b1010 &
b10000100100110001010100010101010010000000101000010011100110010101100111011000010111010001101001011101100110010100101001 2
00
01
#11
0!
b1 #
b1 (
b1011 &
b1000010010001110100010101010101 2
10
11
#12
b10 "
b10 '
b1100 &
b10000100100011101000101010101010010000000101000010011100110010101100111011000010111010001101001011101100110010100101001 2
00
01
#13
b1101 &
b1001110011011110010000001000010011100100110000101101110011000110110100000100000001010000100010001100101011001100110000101110101011011000111010000101001 2
