include/defines.vh

`define DATA_WIDTH 32
`define ADDR_WIDTH 11  


// Immediate Src
`define Imm_I 3'b000 
`define Imm_S 3'b001 
`define Imm_B 3'b010 
`define Imm_U 3'b011 
`define Imm_J 3'b100 

// ALU Operations
`define ALU_ADD 4'b0000
`define ALU_SUB 4'b0001
`define ALU_SLL 4'b0010
`define ALU_SLT 4'b0011
`define ALU_SLTU 4'b0100
`define ALU_XOR 4'b0101
`define ALU_SRL 4'b0110
`define ALU_SRA 4'b0111
`define ALU_OR 4'b1000
`define ALU_AND 4'b1001
`define ALU_LUI 4'b1010

// Control Signals
`define OP_RTYPE  7'b0110011
`define OP_ITYPE  7'b0010011
`define OP_LOAD   7'b0000011
`define OP_STORE  7'b0100011
`define OP_BRANCH 7'b1100011
`define OP_JAL    7'b1101111
`define OP_JALR   7'b1100111
`define OP_LUI    7'b0110111
`define OP_AUIPC  7'b0010111

src/control.v
`include "include/defines.vh"

module control (
    input  wire [6:0] opcode,
    input  wire [2:0] funct3,
    output reg        RegWrite,
    output reg        MemRead,
    output reg        MemWrite,
    output reg        MemtoReg,
    output reg        ALUSrc,
    output reg        Branch,
    output reg        Jump,
    output reg  [1:0] ALUOp,
    output reg  [2:0] ImmSrc
);

  always @(*) begin

    RegWrite = 1'b0;
    MemRead  = 1'b0;
    MemWrite = 1'b0;
    MemtoReg = 1'b0;
    ALUSrc   = 1'b0;
    Branch   = 1'b0;
    Jump     = 1'b0;
    ALUOp    = 2'b00;
    ImmSrc   = 3'b000;

    case (opcode)
      `OP_RTYPE: begin
        RegWrite = 1'b1;
        ALUOp    = 2'b10;
      end

      `OP_ITYPE: begin
        RegWrite = 1'b1;
        ALUSrc   = 1'b1;
        ALUOp    = 2'b10;
        ImmSrc   = `Imm_I;
      end

      `OP_LOAD: begin
        RegWrite = 1'b1;
        MemRead  = 1'b1;
        MemtoReg = 1'b1;
        ALUSrc   = 1'b1;
        ALUOp    = 2'b00;
        ImmSrc   = `Imm_I;
      end

      `OP_STORE: begin
        MemWrite = 1'b1;
        ALUSrc   = 1'b1;
        ALUOp    = 2'b00;
        ImmSrc   = `Imm_S;
      end

      `OP_BRANCH: begin
        Branch = 1'b1;
        ALUOp  = 2'b01;
        ImmSrc = `Imm_B;
      end

      `OP_JAL: begin
        ALUSrc   = 1'b1;
        RegWrite = 1'b1;
        Jump     = 1'b1;
        ALUOp    = 2'b00;
        ImmSrc   = `Imm_J;
      end


      `OP_JALR: begin
        if (funct3 == 3'b000) begin
          ALUSrc   = 1'b1;
          RegWrite = 1'b1;
          Jump     = 1'b1;
          ALUOp    = 2'b00;
          ImmSrc   = `Imm_I;
        end
      end

      `OP_LUI: begin
        RegWrite = 1'b1;
        ALUSrc   = 1'b1;
        ALUOp    = 2'b11;
        ImmSrc   = `Imm_U;
      end

      `OP_AUIPC: begin
        RegWrite = 1'b1;
        ALUSrc   = 1'b1;
        ALUOp    = 2'b00;
        ImmSrc   = `Imm_U;
      end



      default: begin
      end
    endcase
  end

endmodule

tb/control_tb.v
`include "include/defines.vh"

module control_tb;

  reg  [6:0]  opcode;
  reg  [2:0]  funct3;
  wire        RegWrite, MemRead, MemWrite, MemtoReg, ALUSrc, Branch, Jump;
  wire [1:0]  ALUOp;
  wire [2:0]  ImmSrc;

  integer passed, failed;

  control uut (
      .opcode   (opcode),
      .funct3   (funct3),
      .RegWrite (RegWrite),
      .MemRead  (MemRead),
      .MemWrite (MemWrite),
      .MemtoReg (MemtoReg),
      .ALUSrc   (ALUSrc),
      .Branch   (Branch),
      .Jump     (Jump),
      .ALUOp    (ALUOp),
      .ImmSrc   (ImmSrc)
  );

  // now takes 10 inputs (no exp_PCsrc)
  task check_output(
    input        exp_RegWrite,
    input        exp_MemRead,
    input        exp_MemWrite,
    input        exp_MemtoReg,
    input        exp_ALUSrc,
    input        exp_Branch,
    input        exp_Jump,
    input [1:0]  exp_ALUOp,
    input [2:0]  exp_ImmSrc,
    input string message
  );
    if (RegWrite  !== exp_RegWrite ||
        MemRead   !== exp_MemRead  ||
        MemWrite  !== exp_MemWrite ||
        MemtoReg  !== exp_MemtoReg ||
        ALUSrc    !== exp_ALUSrc   ||
        Branch    !== exp_Branch   ||
        Jump      !== exp_Jump     ||
        ALUOp     !== exp_ALUOp    ||
        ImmSrc    !== exp_ImmSrc) begin
      $display("Test failed: %s", message);
      failed = failed + 1;
    end else begin
      $display("Test passed: %s", message);
      passed = passed + 1;
    end
  endtask

  initial begin
    $dumpfile("dump.vcd");
    $dumpvars(0, control_tb);

    passed = 0;
    failed = 0;

    opcode = `OP_RTYPE;
    #10;
    check_output(
      1'b1, 1'b0, 1'b0, 1'b0,  // RegWrite, MemRead, MemWrite, MemtoReg
      1'b0,                    // ALUSrc
      1'b0,                    // Branch
      1'b0,                    // Jump
      2'b10,                   // ALUOp
      3'b000,                  // ImmSrc
      "R-type ADD"
    );

    opcode = `OP_ITYPE;
    #10;
    check_output(1'b1,1'b0,1'b0,1'b0, 1'b1, 1'b0, 1'b0, 2'b10, `Imm_I, "I-type ADDI");

    opcode = `OP_LOAD;
    #10;
    check_output(1'b1,1'b1,1'b0,1'b1, 1'b1, 1'b0, 1'b0, 2'b00, `Imm_I, "Load LW");

    opcode = `OP_STORE;
    #10;
    check_output(1'b0,1'b0,1'b1,1'b0, 1'b1, 1'b0, 1'b0, 2'b00, `Imm_S, "Store SW");

    opcode = `OP_BRANCH;
    #10;
    check_output(1'b0,1'b0,1'b0,1'b0, 1'b0, 1'b1, 1'b0, 2'b01, `Imm_B, "Branch BEQ");

    opcode = `OP_JAL;
    #10;
    check_output(1'b1,1'b0,1'b0,1'b0, 1'b1, 1'b0, 1'b1, 2'b00, `Imm_J, "Jump JAL");

    opcode = `OP_JALR;
    funct3 = 3'b000;
    #10;
    check_output(1'b1,1'b0,1'b0,1'b0, 1'b1, 1'b0, 1'b1, 2'b00, `Imm_I, "Jump JALR");

    opcode = `OP_LUI;
    #10;
    check_output(1'b1,1'b0,1'b0,1'b0, 1'b1, 1'b0, 1'b0, 2'b11, `Imm_U, "Load Upper LUI");

    opcode = `OP_AUIPC;
    #10;
    check_output(1'b1,1'b0,1'b0,1'b0, 1'b1, 1'b0, 1'b0, 2'b00, `Imm_U, "Add Upper Immediate AUIPC");

    if (failed == 0) begin
      $display("All tests passed!");
    end else begin
      $display("%0d tests passed, %0d tests failed.", passed, failed);
    end
    $finish;
  end

endmodule

waves/control.vcd
$date
	Sun Jul  6 11:27:25 2025
$end
$version
	Icarus Verilog
$end
$timescale
	1s
$end
$scope module control_tb $end
$var wire 1 ! RegWrite $end
$var wire 1 " MemtoReg $end
$var wire 1 # MemWrite $end
$var wire 1 $ MemRead $end
$var wire 1 % Jump $end
$var wire 3 & ImmSrc [2:0] $end
$var wire 1 ' Branch $end
$var wire 1 ( ALUSrc $end
$var wire 2 ) ALUOp [1:0] $end
$var reg 3 * funct3 [2:0] $end
$var reg 7 + opcode [6:0] $end
$var integer 32 , failed [31:0] $end
$var integer 32 - passed [31:0] $end
$scope module uut $end
$var wire 3 . funct3 [2:0] $end
$var wire 7 / opcode [6:0] $end
$var reg 2 0 ALUOp [1:0] $end
$var reg 1 ( ALUSrc $end
$var reg 1 ' Branch $end
$var reg 3 1 ImmSrc [2:0] $end
$var reg 1 % Jump $end
$var reg 1 $ MemRead $end
$var reg 1 # MemWrite $end
$var reg 1 " MemtoReg $end
$var reg 1 ! RegWrite $end
$upscope $end
$scope task check_output $end
$var reg 2 2 exp_ALUOp [1:0] $end
$var reg 1 3 exp_ALUSrc $end
$var reg 1 4 exp_Branch $end
$var reg 3 5 exp_ImmSrc [2:0] $end
$var reg 1 6 exp_Jump $end
$var reg 1 7 exp_MemRead $end
$var reg 1 8 exp_MemWrite $end
$var reg 1 9 exp_MemtoReg $end
$var reg 1 : exp_RegWrite $end
$upscope $end
$upscope $end
$enddefinitions $end
$comment Show the parameter values. $end
$dumpall
$end
#0
$dumpvars
x:
x9
x8
x7
x6
bx 5
x4
x3
bx 2
b0 1
b10 0
b110011 /
bx .
b0 -
b0 ,
b110011 +
bx *
b10 )
0(
0'
b0 &
0%
0$
0#
0"
1!
$end
#10
1(
b10 )
b10 0
1!
b10011 +
b10011 /
b1 -
b0 5
b10 2
06
04
03
09
08
07
1:
#20
1"
1$
b0 )
b0 0
1(
1!
b11 +
b11 /
b10 -
13
#30
b1 &
b1 1
1#
1(
0"
0$
0!
b100011 +
b100011 /
b11 -
b0 2
19
17
#40
b1 )
b1 0
1'
b10 &
b10 1
0(
0#
b1100011 +
b1100011 /
b100 -
b1 5
09
18
07
0:
#50
1%
1!
1(
b100 &
b100 1
b0 )
b0 0
0'
b1101111 +
b1101111 /
b101 -
b10 5
b1 2
14
03
08
#60
b0 &
b0 1
1%
1(
1!
b0 *
b0 .
b1100111 +
b1100111 /
b110 -
b100 5
b0 2
16
04
13
1:
#70
b11 &
b11 1
b11 )
b11 0
0%
1(
1!
b110111 +
b110111 /
b111 -
b0 5
#80
b11 &
b11 1
b0 )
b0 0
1(
1!
b10111 +
b10111 /
b1000 -
b11 5
b11 2
06
#90
b1001 -
b0 2
