include/defines.vh

`define DATA_WIDTH 32
`define ADDR_WIDTH 11  


// Immediate Src
`define Imm_I 3'b000 
`define Imm_S 3'b001 
`define Imm_B 3'b010 
`define Imm_U 3'b011 
`define Imm_J 3'b100 

// ALU Operations
`define ALU_ADD 4'b0000
`define ALU_SUB 4'b0001
`define ALU_SLL 4'b0010
`define ALU_SLT 4'b0011
`define ALU_SLTU 4'b0100
`define ALU_XOR 4'b0101
`define ALU_SRL 4'b0110
`define ALU_SRA 4'b0111
`define ALU_OR 4'b1000
`define ALU_AND 4'b1001
`define ALU_LUI 4'b1010

// Control Signals
`define OP_RTYPE  7'b0110011
`define OP_ITYPE  7'b0010011
`define OP_LOAD   7'b0000011
`define OP_STORE  7'b0100011
`define OP_BRANCH 7'b1100011
`define OP_JAL    7'b1101111
`define OP_JALR   7'b1100111
`define OP_LUI    7'b0110111
`define OP_AUIPC  7'b0010111
`define OP_SYSTEM 7'b1110011

src/control.v
`include "include/defines.vh"

module control #(
    parameter DATA_WIDTH = 32
) (
    input  wire [DATA_WIDTH-1:0] instr,
    input  wire                  ALUreg,
    input  wire                  ALUimm,
    input  wire                  Branch,
    input  wire                  JAL,
    input  wire                  JALR,
    input  wire                  LUI,
    input  wire                  AUIPC,
    input  wire                  Load,
    input  wire                  Store,
    input  wire                  SYSTEM,
    output reg                   MemRead,
    output reg                   MemWrite,
    output reg                   MemtoReg,
    output reg                   ALUSrc,
    output reg                   BranchSig,
    output reg                   Jump,
    output reg  [           1:0] ALUOp,
    output reg  [           2:0] ImmSrc
);

  wire funct3 = instr[14:12];

  always @(*) begin

    MemRead   = 1'b0;
    MemWrite  = 1'b0;
    MemtoReg  = 1'b0;
    ALUSrc    = 1'b0;
    BranchSig = 1'b0;
    Jump      = 1'b0;
    ALUOp     = 2'b00;
    ImmSrc    = 3'b000;

    if (ALUreg) begin
      ALUOp = 2'b10;  // R-type
    end

    if (ALUimm) begin
      ALUSrc = 1'b1;  // I-type
      ALUOp  = 2'b10;
      ImmSrc = `Imm_I;
    end

    if (Load) begin
      MemRead  = 1'b1;
      MemtoReg = 1'b1;
      ALUSrc   = 1'b1;
      ALUOp    = 2'b00;
      ImmSrc   = `Imm_I;
    end

    if (Store) begin
      MemWrite = 1'b1;
      ALUSrc   = 1'b1;
      ALUOp    = 2'b00;
      ImmSrc   = `Imm_S;
    end

    if (Branch) begin
      BranchSig = 1'b1;
      ALUOp = 2'b01;
      ImmSrc = `Imm_B;
    end

    if (JAL) begin
      ALUSrc = 1'b1;
      Jump   = 1'b1;
      ALUOp  = 2'b00;
      ImmSrc = `Imm_J;
    end

    if (JALR) begin
      ALUSrc = 1'b1;
      Jump   = 1'b1;
      ALUOp  = 2'b00;
      ImmSrc = `Imm_I;
    end

    if (LUI) begin
      ALUSrc = 1'b1;
      ALUOp  = 2'b11;
      ImmSrc = `Imm_U;
    end

    if (AUIPC) begin
      ALUSrc = 1'b1;
      ALUOp  = 2'b00;
      ImmSrc = `Imm_U;
    end

    if (SYSTEM) begin
      // not done yet
    end

  end

endmodule

tb/control_tb.v
`timescale 1ns / 1ps
`include "include/defines.vh"

module control_tb;

  // Inputs
  reg [31:0] instr;
  reg ALUreg, ALUimm, Branch, JAL, JALR, LUI, AUIPC, Load, Store, SYSTEM;

  // Outputs
  wire MemRead, MemWrite, MemtoReg, ALUSrc, BranchSig, Jump;
  wire [1:0] ALUOp;
  wire [2:0] ImmSrc;

  // DUT
  control uut (
      .instr(instr),
      .ALUreg(ALUreg),
      .ALUimm(ALUimm),
      .Branch(Branch),
      .JAL(JAL),
      .JALR(JALR),
      .LUI(LUI),
      .AUIPC(AUIPC),
      .Load(Load),
      .Store(Store),
      .SYSTEM(SYSTEM),
      .MemRead(MemRead),
      .MemWrite(MemWrite),
      .MemtoReg(MemtoReg),
      .ALUSrc(ALUSrc),
      .BranchSig(BranchSig),
      .Jump(Jump),
      .ALUOp(ALUOp),
      .ImmSrc(ImmSrc)
  );

  integer failed, passed;

  task reset_inputs;
    begin
      {ALUreg, ALUimm, Branch, JAL, JALR, LUI, AUIPC, Load, Store, SYSTEM} = 10'b0;
      instr = 32'b0;
    end
  endtask

  task assert_control(input exp_MemRead, exp_MemWrite, exp_MemtoReg, input exp_ALUSrc,
                      exp_BranchSig, exp_Jump, input [1:0] exp_ALUOp, input [2:0] exp_ImmSrc,
                      input [127:0] label);
    #1;
    if (MemRead   !== exp_MemRead   ||
        MemWrite  !== exp_MemWrite  ||
        MemtoReg  !== exp_MemtoReg  ||
        ALUSrc    !== exp_ALUSrc    ||
        BranchSig !== exp_BranchSig ||
        Jump      !== exp_Jump      ||
        ALUOp     !== exp_ALUOp     ||
        ImmSrc    !== exp_ImmSrc) begin
      $display("FAIL [%s] at time %0t", label, $time);
      $display(
          "   Got     : MemRead=%b, MemWrite=%b, MemtoReg=%b, ALUSrc=%b, Branch=%b, Jump=%b, ALUOp=%02b, ImmSrc=%03b",
          MemRead, MemWrite, MemtoReg, ALUSrc, BranchSig, Jump, ALUOp, ImmSrc);
      $display(
          "   Expected: MemRead=%b, MemWrite=%b, MemtoReg=%b, ALUSrc=%b, Branch=%b, Jump=%b, ALUOp=%02b, ImmSrc=%03b",
          exp_MemRead, exp_MemWrite, exp_MemtoReg, exp_ALUSrc, exp_BranchSig, exp_Jump, exp_ALUOp,
          exp_ImmSrc);
      failed = failed + 1;
    end else begin
      $display("PASS [%s]", label);
      passed = passed + 1;
    end
  endtask

  initial begin
    $display("Starting control unit tests...\n");
    $dumpfile("dump.vcd");
    $dumpvars(0, control_tb);

    passed = 0;
    failed = 0;

    // R-type
    reset_inputs();
    ALUreg = 1;
    #1 assert_control(0, 0, 0, 0, 0, 0, 2'b10, 3'b000, "R-type");

    // I-type (ALU imm)
    reset_inputs();
    ALUimm = 1;
    #1 assert_control(0, 0, 0, 1, 0, 0, 2'b10, `Imm_I, "I-type");

    // Load
    reset_inputs();
    Load = 1;
    #1 assert_control(1, 0, 1, 1, 0, 0, 2'b00, `Imm_I, "Load");

    // Store
    reset_inputs();
    Store = 1;
    #1 assert_control(0, 1, 0, 1, 0, 0, 2'b00, `Imm_S, "Store");

    // Branch
    reset_inputs();
    Branch = 1;
    #1 assert_control(0, 0, 0, 0, 1, 0, 2'b01, `Imm_B, "Branch");

    // JAL
    reset_inputs();
    JAL = 1;
    #1 assert_control(0, 0, 0, 1, 0, 1, 2'b00, `Imm_J, "JAL");

    // JALR (only if funct3 = 000)
    reset_inputs();
    JALR = 1;
    instr[14:12] = 3'b000;
    #1 assert_control(0, 0, 0, 1, 0, 1, 2'b00, `Imm_I, "JALR funct3=000");

    // LUI
    reset_inputs();
    LUI = 1;
    #1 assert_control(0, 0, 0, 1, 0, 0, 2'b11, `Imm_U, "LUI");

    // AUIPC
    reset_inputs();
    AUIPC = 1;
    #1 assert_control(0, 0, 0, 1, 0, 0, 2'b00, `Imm_U, "AUIPC");

    $display("\nSummary of control unit tests:");
    $display("Total tests: %d", passed + failed);
    $display("Passed: %d", passed);
    $display("Failed: %d", failed);
    $finish;
  end

endmodule

waves/control.vcd
$date
	Fri Aug  8 11:47:19 2025
$end
$version
	Icarus Verilog
$end
$timescale
	1ps
$end
$scope module control_tb $end
$var wire 1 ! MemtoReg $end
$var wire 1 " MemWrite $end
$var wire 1 # MemRead $end
$var wire 1 $ Jump $end
$var wire 3 % ImmSrc [2:0] $end
$var wire 1 & BranchSig $end
$var wire 1 ' ALUSrc $end
$var wire 2 ( ALUOp [1:0] $end
$var reg 1 ) ALUimm $end
$var reg 1 * ALUreg $end
$var reg 1 + AUIPC $end
$var reg 1 , Branch $end
$var reg 1 - JAL $end
$var reg 1 . JALR $end
$var reg 1 / LUI $end
$var reg 1 0 Load $end
$var reg 1 1 SYSTEM $end
$var reg 1 2 Store $end
$var reg 32 3 instr [31:0] $end
$var integer 32 4 failed [31:0] $end
$var integer 32 5 passed [31:0] $end
$scope module uut $end
$var wire 1 ) ALUimm $end
$var wire 1 * ALUreg $end
$var wire 1 + AUIPC $end
$var wire 1 , Branch $end
$var wire 1 - JAL $end
$var wire 1 . JALR $end
$var wire 1 / LUI $end
$var wire 1 0 Load $end
$var wire 1 1 SYSTEM $end
$var wire 1 2 Store $end
$var wire 32 6 instr [31:0] $end
$var wire 1 7 funct3 $end
$var parameter 32 8 DATA_WIDTH $end
$var reg 2 9 ALUOp [1:0] $end
$var reg 1 ' ALUSrc $end
$var reg 1 & BranchSig $end
$var reg 3 : ImmSrc [2:0] $end
$var reg 1 $ Jump $end
$var reg 1 # MemRead $end
$var reg 1 " MemWrite $end
$var reg 1 ! MemtoReg $end
$upscope $end
$scope task assert_control $end
$var reg 2 ; exp_ALUOp [1:0] $end
$var reg 1 < exp_ALUSrc $end
$var reg 1 = exp_BranchSig $end
$var reg 3 > exp_ImmSrc [2:0] $end
$var reg 1 ? exp_Jump $end
$var reg 1 @ exp_MemRead $end
$var reg 1 A exp_MemWrite $end
$var reg 1 B exp_MemtoReg $end
$var reg 128 C label [127:0] $end
$upscope $end
$scope task reset_inputs $end
$upscope $end
$upscope $end
$enddefinitions $end
$comment Show the parameter values. $end
$dumpall
b100000 8
$end
#0
$dumpvars
bx C
xB
xA
x@
x?
bx >
x=
x<
bx ;
b0 :
b10 9
07
b0 6
b0 5
b0 4
b0 3
02
01
00
0/
0.
0-
0,
0+
1*
0)
b10 (
0'
0&
b0 %
0$
0#
0"
0!
$end
#1000
b10100100010110101110100011110010111000001100101 C
b0 >
b10 ;
0?
0=
0<
0B
0A
0@
#2000
1'
b10 (
b10 9
1)
0*
b1 5
#3000
b10010010010110101110100011110010111000001100101 C
1<
#4000
1!
1#
b0 (
b0 9
1'
10
0)
b10 5
#5000
b1001100011011110110000101100100 C
b0 ;
1B
1@
#6000
b1 %
b1 :
1"
1'
0!
0#
12
00
b11 5
#7000
b101001101110100011011110111001001100101 C
b1 >
0B
1A
0@
#8000
b1 (
b1 9
1&
b10 %
b10 :
0'
0"
1,
02
b100 5
#9000
b10000100111001001100001011011100110001101101000 C
b10 >
b1 ;
1=
0<
0A
#10000
1$
1'
b100 %
b100 :
b0 (
b0 9
0&
1-
0,
b101 5
#11000
b10010100100000101001100 C
b100 >
b0 ;
1?
0=
1<
#12000
b0 %
b0 :
1$
1'
1.
0-
b110 5
#13000
b10010100100000101001100010100100010000001100110011101010110111001100011011101000011001100111101001100000011000000110000 C
b0 >
#14000
b11 %
b11 :
b11 (
b11 9
0$
1'
1/
0.
b111 5
#15000
b10011000101010101001001 C
b11 >
b11 ;
0?
#16000
b11 %
b11 :
b0 (
b0 9
1'
1+
0/
b1000 5
#17000
b100000101010101010010010101000001000011 C
b0 ;
#18000
b1001 5
