include/defines.vh

`define DATA_WIDTH 32
`define ADDR_WIDTH 11  


// Immediate Src
`define Imm_I 3'b000 
`define Imm_S 3'b001 
`define Imm_B 3'b010 
`define Imm_U 3'b011 
`define Imm_J 3'b100 

// ALU Operations
`define ALU_ADD 4'b0000
`define ALU_SUB 4'b0001
`define ALU_SLL 4'b0010
`define ALU_SLT 4'b0011
`define ALU_SLTU 4'b0100
`define ALU_XOR 4'b0101
`define ALU_SRL 4'b0110
`define ALU_SRA 4'b0111
`define ALU_OR 4'b1000
`define ALU_AND 4'b1001
`define ALU_LUI 4'b1010

// Control Signals
`define OP_RTYPE  7'b0110011
`define OP_ITYPE  7'b0010011
`define OP_LOAD   7'b0000011
`define OP_STORE  7'b0100011
`define OP_BRANCH 7'b1100011
`define OP_JAL    7'b1101111
`define OP_JALR   7'b1100111
`define OP_LUI    7'b0110111
`define OP_AUIPC  7'b0010111
`define OP_SYSTEM 7'b1110011

src/decoder.v
`timescale 1ns / 1ps
`include "include/defines.vh"

module decoder #(
    parameter DATA_WIDTH = 32
) (
    input wire [DATA_WIDTH-1:0] instr,
    output wire ALUreg,
    output wire regWrite,
    output wire JAL,
    output wire JALR,
    output wire Branch,
    output wire LUI,
    output wire AUIPC,
    output wire ALUimm,
    output wire Load,
    output wire Store
);


  wire [6:0] opcode = instr[6:0];

  assign ALUreg =  (opcode == `OP_RTYPE); // rd <- rs1 OP rs2   
  assign ALUimm =  (opcode == `OP_ITYPE); // rd <- rs1 OP Iimm
  assign Branch =  (opcode == `OP_BRANCH); // if(rs1 OP rs2) PC<-PC+Bimm
  assign JALR   =  (opcode == `OP_JALR && instr[14:12] == 3'b000); // rd <- PC+4; PC<-rs1+Iimm
  assign JAL    =  (opcode == `OP_JAL); // rd <- PC+4; PC<-PC+Jimm
  assign AUIPC  =  (opcode == `OP_AUIPC); // rd <- PC + Uimm
  assign LUI    =  (opcode == `OP_LUI); // rd <- Uimm   
  assign Load   =  (opcode == `OP_LOAD); // rd <- mem[rs1+Iimm]
  assign Store  =  (opcode == `OP_STORE); // mem[rs1+Simm] <- rs2
  assign SYSTEM =  (opcode == `OP_SYSTEM); // special

  assign regWrite = ALUreg || ALUimm || Load || LUI || AUIPC || JAL || JALR;

endmodule

tb/decoder_tb.v
`timescale 1ns / 1ps

module decoder_tb;

  // Inputs
  reg [31:0] instr;

  // Outputs
  wire ALUreg, regWrite, JAL, JALR, Branch, LUI, AUIPC, ALUimm, Load, Store;

  // Instantiate the Unit Under Test (UUT)
  decoder uut (
      .instr(instr),
      .ALUreg(ALUreg),
      .regWrite(regWrite),
      .JAL(JAL),
      .JALR(JALR),
      .Branch(Branch),
      .LUI(LUI),
      .AUIPC(AUIPC),
      .ALUimm(ALUimm),
      .Load(Load),
      .Store(Store)
  );

  integer failed, passed;


  task check_output;
    input string test_name;
    input [31:0] instr_val;
    input exp_ALUreg, exp_ALUimm, exp_Branch, exp_JAL, exp_JALR;
    input exp_LUI, exp_AUIPC, exp_Load, exp_Store, exp_regWrite;

    begin
      instr = instr_val;
      #1;

      $display("Instr = %b, Test = %s", instr, test_name);

      if (ALUreg !== exp_ALUreg)
        $display("ASSERTION FAILED: ALUreg   expected %b, got %b", exp_ALUreg, ALUreg);
      if (ALUimm !== exp_ALUimm)
        $display("ASSERTION FAILED: ALUimm   expected %b, got %b", exp_ALUimm, ALUimm);
      if (Branch !== exp_Branch)
        $display("ASSERTION FAILED: Branch   expected %b, got %b", exp_Branch, Branch);
      if (JAL !== exp_JAL) $display("ASSERTION FAILED: JAL      expected %b, got %b", exp_JAL, JAL);
      if (JALR !== exp_JALR)
        $display("ASSERTION FAILED: JALR     expected %b, got %b", exp_JALR, JALR);
      if (LUI !== exp_LUI) $display("ASSERTION FAILED: LUI      expected %b, got %b", exp_LUI, LUI);
      if (AUIPC !== exp_AUIPC)
        $display("ASSERTION FAILED: AUIPC    expected %b, got %b", exp_AUIPC, AUIPC);
      if (Load !== exp_Load)
        $display("ASSERTION FAILED: Load     expected %b, got %b", exp_Load, Load);
      if (Store !== exp_Store)
        $display("ASSERTION FAILED: Store    expected %b, got %b", exp_Store, Store);
      if (regWrite !== exp_regWrite)
        $display("ASSERTION FAILED: regWrite expected %b, got %b", exp_regWrite, regWrite);

      if (ALUreg === exp_ALUreg && ALUimm === exp_ALUimm &&
        Branch === exp_Branch && JAL === exp_JAL && JALR === exp_JALR &&
        LUI === exp_LUI && AUIPC === exp_AUIPC && Load === exp_Load &&
        Store === exp_Store && regWrite === exp_regWrite) begin
        passed = passed + 1;
        $display("Test passed: %s", test_name);
      end else begin
        failed = failed + 1;
        $display("Test failed: %s", test_name);
      end

    end
  endtask

  initial begin
    $dumpfile("dump.vcd");
    $dumpvars(0, decoder_tb);
    $display("Starting Decoder Testbench with Assertions\n");

    passed = 0;
    failed = 0;

    // R-type: add x3, x1, x2 (0110011)
    check_output("R-type: add x3, x1, x2", 32'b0000000_00010_00001_000_00011_0110011, 1, 0, 0, 0, 0,
                 0, 0, 0, 0, 1);

    // I-type: addi x3, x1, 5 (0010011)
    check_output("I-type: addi x3, x1, 5", 32'b000000000101_00001_000_00011_0010011, 0, 1, 0, 0, 0,
                 0, 0, 0, 0, 1);

    // Load: lw x3, 4(x1) (0000011)
    check_output("Load: lw x3, 4(x1)", 32'b000000000100_00001_010_00011_0000011, 0, 0, 0, 0, 0, 0,
                 0, 1, 0, 1);

    // Store: sw x3, 4(x1) (0100011)
    check_output("Store: sw x3, 4(x1)", 32'b0000000_00011_00001_010_00100_0100011, 0, 0, 0, 0, 0, 0,
                 0, 0, 1, 0);

    // Branch: beq x1, x3, offset (1100011)
    check_output("Branch: beq x1, x3, offset", 32'b0000000_00011_00001_000_00010_1100011, 0, 0, 1,
                 0, 0, 0, 0, 0, 0, 0);

    // JALR: jalr x3, 4(x1) (1100111)
    check_output("JALR: jalr x3, 4(x1)", 32'b000000000100_00001_000_00011_1100111, 0, 0, 0, 0, 1, 0,
                 0, 0, 0, 1);

    // JAL: jal x3, offset (1101111)
    check_output("JAL: jal x3, offset", 32'b000000000000000000000_00011_1101111, 0, 0, 0, 1, 0, 0,
                 0, 0, 0, 1);

    // LUI: lui x3, 1 (0110111)
    check_output("LUI: lui x3, 1", 32'b00000000000000000001_00011_0110111, 0, 0, 0, 0, 0, 1, 0, 0,
                 0, 1);

    // AUIPC: auipc x3, 1 (0010111)
    check_output("AUIPC: auipc x3, 1", 32'b00000000000000000001_00011_0010111, 0, 0, 0, 0, 0, 0, 1,
                 0, 0, 1);

    $display("\nDecoder Testbench Summary:");
    $display("Total Tests: %d", passed + failed);
    $display("Passed: %d", passed);
    $display("Failed: %d", failed);

    $finish;
  end

endmodule

waves/decoder.vcd
$date
	Fri Aug  8 11:40:31 2025
$end
$version
	Icarus Verilog
$end
$timescale
	1ps
$end
$scope module decoder_tb $end
$var wire 1 ! regWrite $end
$var wire 1 " Store $end
$var wire 1 # Load $end
$var wire 1 $ LUI $end
$var wire 1 % JALR $end
$var wire 1 & JAL $end
$var wire 1 ' Branch $end
$var wire 1 ( AUIPC $end
$var wire 1 ) ALUreg $end
$var wire 1 * ALUimm $end
$var reg 32 + instr [31:0] $end
$var integer 32 , failed [31:0] $end
$var integer 32 - passed [31:0] $end
$scope module uut $end
$var wire 1 % JALR $end
$var wire 32 . instr [31:0] $end
$var wire 1 ! regWrite $end
$var wire 7 / opcode [6:0] $end
$var wire 1 " Store $end
$var wire 1 0 SYSTEM $end
$var wire 1 # Load $end
$var wire 1 $ LUI $end
$var wire 1 & JAL $end
$var wire 1 ' Branch $end
$var wire 1 ( AUIPC $end
$var wire 1 ) ALUreg $end
$var wire 1 * ALUimm $end
$var parameter 32 1 DATA_WIDTH $end
$upscope $end
$scope task check_output $end
$var reg 1 2 exp_ALUimm $end
$var reg 1 3 exp_ALUreg $end
$var reg 1 4 exp_AUIPC $end
$var reg 1 5 exp_Branch $end
$var reg 1 6 exp_JAL $end
$var reg 1 7 exp_JALR $end
$var reg 1 8 exp_LUI $end
$var reg 1 9 exp_Load $end
$var reg 1 : exp_Store $end
$var reg 1 ; exp_regWrite $end
$var reg 32 < instr_val [31:0] $end
$upscope $end
$upscope $end
$enddefinitions $end
$comment Show the parameter values. $end
$dumpall
b100000 1
$end
#0
$dumpvars
b1000001000000110110011 <
1;
0:
09
08
07
06
05
04
13
02
00
b110011 /
b1000001000000110110011 .
b0 -
b0 ,
b1000001000000110110011 +
0*
1)
0(
0'
0&
0%
0$
0#
0"
1!
$end
#1000
0)
1*
b10011 /
b10100001000000110010011 +
b10100001000000110010011 .
12
03
b10100001000000110010011 <
b1 -
#2000
0*
1#
b11 /
b10000001010000110000011 +
b10000001010000110000011 .
19
02
b10000001010000110000011 <
b10 -
#3000
0!
0#
1"
b100011 /
b1100001010001000100011 +
b1100001010001000100011 .
0;
1:
09
b1100001010001000100011 <
b11 -
#4000
1'
0"
b1100011 /
b1100001000000101100011 +
b1100001000000101100011 .
0:
15
b1100001000000101100011 <
b100 -
#5000
1!
1%
0'
b1100111 /
b10000001000000111100111 +
b10000001000000111100111 .
1;
17
05
b10000001000000111100111 <
b101 -
#6000
0%
1&
b1101111 /
b111101111 +
b111101111 .
07
16
b111101111 <
b110 -
#7000
1!
0&
1$
b110111 /
b1000110110111 +
b1000110110111 .
18
06
b1000110110111 <
b111 -
#8000
1(
0$
b10111 /
b1000110010111 +
b1000110010111 .
14
08
b1000110010111 <
b1000 -
#9000
b1001 -
