include/defines.vh
`define DATA_WIDTH 32
`define ADDR_WIDTH 11  

// Immediate Src
`define Imm_I 3'b000 
`define Imm_S 3'b001 
`define Imm_B 3'b010 
`define Imm_U 3'b011 
`define Imm_J 3'b100 
`define Imm_NONE 3'b111

// ALU Operations
`define ALU_ADD 4'b0000
`define ALU_SUB 4'b0001
`define ALU_SLL 4'b0010
`define ALU_SLT 4'b0011
`define ALU_SLTU 4'b0100
`define ALU_XOR 4'b0101
`define ALU_SRL 4'b0110
`define ALU_SRA 4'b0111
`define ALU_OR 4'b1000
`define ALU_AND 4'b1001
`define ALU_LUI 4'b1010

// Control Signals
`define OP_RTYPE 7'b0110011
`define OP_ITYPE 7'b0010011
`define OP_LOAD 7'b0000011
`define OP_STORE 7'b0100011
`define OP_BRANCH 7'b1100011
`define OP_JAL 7'b1101111
`define OP_JALR 7'b1100111
`define OP_LUI 7'b0110111
`define OP_AUIPC 7'b0010111
`define OP_SYSTEM 7'b1110011

src/imm_gen.v
`include "include/defines.vh"

module imm_gen (
    input  wire [31:0] instr,
    input  wire [ 2:0] imm_sel,
    output reg  [31:0] imm_out
);
  wire [31:0] i_imm = {{20{instr[31]}}, instr[31:20]};
  wire [31:0] s_imm = {{20{instr[31]}}, instr[31:25], instr[11:7]};
  wire [31:0] b_imm = {{19{instr[31]}}, instr[31], instr[7], instr[30:25], instr[11:8],1'b0 };
  wire [31:0] u_imm = {instr[31:12], 12'b0};
  wire [31:0] j_imm = {{11{instr[31]}}, instr[31], instr[19:12], instr[20], instr[30:21], 1'b0};

  always @(*) begin
    case (imm_sel)
      `Imm_I:  imm_out = i_imm;
      `Imm_S:  imm_out = s_imm;
      `Imm_B:  imm_out = b_imm;
      `Imm_U:  imm_out = u_imm;
      `Imm_J:  imm_out = j_imm;
      default: imm_out = 32'b0;
    endcase
  end
endmodule

tb/imm_gen_tb.v
`timescale 1ns / 1ps

module imm_gen_tb;

  reg  [31:0] instr;
  reg  [ 2:0] imm_sel;

  wire [31:0] imm_out;


  reg  [31:0] expected;
  integer passed, failed;

  imm_gen uut (
      .instr  (instr),
      .imm_sel(imm_sel),
      .imm_out(imm_out)
  );


  task check;
    input [31:0] test_instr;
    input [2:0] sel;
    input [31:0] exp;
    begin
      instr   = test_instr;
      imm_sel = sel;
      #2;
      expected = exp;

      if (imm_out === expected) begin
        passed = passed + 1;
        $display("PASS: sel=%b instr=0x%08h -> imm_out=0x%08h", sel, instr, imm_out);
      end else begin
        failed = failed + 1;
        $error("FAIL: sel=%b instr=0x%08h -> expected=0x%08h, got=0x%08h", sel, instr, expected,
               imm_out);
      end
    end
  endtask

  initial begin

    $dumpfile("dump.vcd");
    $dumpvars(0, imm_gen_tb);


    passed = 0;
    failed = 0;

    $display("\n--- IMMGEN Enhanced Testbench Start ---\n");

    // I-Type Immediates
    check(32'h7FF00000, 3'b000, 32'h000007FF);  // +2047
    check(32'h80000000, 3'b000, 32'hFFFFF800);  // -2048
    check(32'h12300000, 3'b000, 32'h00000123);  // +0x123 (bits[31:20]=0x123)

    // S-Type Store Offsets
    check(32'h0000A223, 3'b001, 32'h00000004);  // +4  (imm[11:5]=0, imm[4:0]=00100)
    check(32'hFE002423, 3'b001, 32'hFFFFFFE8);  // -24 (imm[11:5]=1111111, imm[4:0]=00111)

    // B-Type Branch Offsets
    check(32'h04000063, 3'b010, 32'h00000040);  // +16 (imm=0x010 <<1)
    check(32'hFE0000E3, 3'b010, -32);  // -32 (imm=0xFF0 <<1 signed)

    // U-Type Upper Immediates
    check(32'h12345000, 3'b011, 32'h12345000);  // imm[31:12]=0x12345
    check(32'hFFFFF000, 3'b011, 32'hFFFFF000);  // imm[31:12]=0xFFFFF

    // J-Type Jump Offsets
    check(32'h004000EF, 3'b100, 32'd4);  // +1024 (j10:1=0b1000000000)
    check(32'h801FF06F, 3'b100, -2048);  // -2048 (imm21 two's complement)

    $display("\n--- IMMGEN Test Results ---");
    $display("Passed: %0d, Failed: %0d", passed, failed);
    if (failed > 0) begin
      $display("Some tests failed.");
      $fatal;
    end else begin
      $display("All tests passed!\n");
    end
    $finish;
  end
endmodule

waves/imm_gen.vcd
$date
	Tue Aug 26 21:19:24 2025
$end
$version
	Icarus Verilog
$end
$timescale
	1ps
$end
$scope module imm_gen_tb $end
$var wire 32 ! imm_out [31:0] $end
$var reg 32 " expected [31:0] $end
$var reg 3 # imm_sel [2:0] $end
$var reg 32 $ instr [31:0] $end
$var integer 32 % failed [31:0] $end
$var integer 32 & passed [31:0] $end
$scope module uut $end
$var wire 3 ' imm_sel [2:0] $end
$var wire 32 ( instr [31:0] $end
$var wire 32 ) u_imm [31:0] $end
$var wire 32 * s_imm [31:0] $end
$var wire 32 + j_imm [31:0] $end
$var wire 32 , i_imm [31:0] $end
$var wire 32 - b_imm [31:0] $end
$var reg 32 . imm_out [31:0] $end
$upscope $end
$scope task check $end
$var reg 32 / exp [31:0] $end
$var reg 3 0 sel [2:0] $end
$var reg 32 1 test_instr [31:0] $end
$upscope $end
$upscope $end
$enddefinitions $end
$comment Show the parameter values. $end
$dumpall
$end
#0
$dumpvars
b1111111111100000000000000000000 1
b0 0
b11111111111 /
b11111111111 .
b11111100000 -
b11111111111 ,
b111111111110 +
b11111100000 *
b1111111111100000000000000000000 )
b1111111111100000000000000000000 (
b0 '
b0 &
b0 %
b1111111111100000000000000000000 $
b0 #
bx "
b11111111111 !
$end
#2000
b11111111111111111111100000000000 !
b11111111111111111111100000000000 .
b11111111111111111111100000000000 ,
b11111111111111111111100000000000 *
b11111111111111111111000000000000 -
b10000000000000000000000000000000 )
b11111111111100000000000000000000 +
b10000000000000000000000000000000 $
b10000000000000000000000000000000 (
b11111111111111111111100000000000 /
b10000000000000000000000000000000 1
b1 &
b11111111111 "
#4000
b100100011 !
b100100011 .
b100100011 ,
b100100000 *
b100100000 -
b10010001100000000000000000000 )
b100100100010 +
b10010001100000000000000000000 $
b10010001100000000000000000000 (
b100100011 /
b10010001100000000000000000000 1
b10 &
b11111111111111111111100000000000 "
#6000
b100 !
b100 .
b0 ,
b100 *
b100 -
b1010000000000000 )
b1010000000000000 +
b1 #
b1 '
b1010001000100011 $
b1010001000100011 (
b100 /
b1 0
b1010001000100011 1
b11 &
b100100011 "
#8000
b11111111111111111111111111101000 !
b11111111111111111111111111101000 .
b11111111111111111111111111100000 ,
b11111111111111111111111111101000 *
b11111111111111111111011111101000 -
b11111110000000000010000000000000 )
b11111111111100000010011111100000 +
b11111110000000000010010000100011 $
b11111110000000000010010000100011 (
b11111111111111111111111111101000 /
b11111110000000000010010000100011 1
b100 &
b100 "
#10000
b1000000 !
b1000000 .
b1000000 ,
b1000000 *
b1000000 -
b100000000000000000000000000 )
b1000000 +
b10 #
b10 '
b100000000000000000001100011 $
b100000000000000000001100011 (
b1000000 /
b10 0
b100000000000000000001100011 1
b101 &
b11111111111111111111111111101000 "
#12000
b11111111111111111111111111100000 !
b11111111111111111111111111100000 .
b11111111111111111111111111100000 ,
b11111111111111111111111111100001 *
b11111111111111111111111111100000 -
b11111110000000000000000000000000 )
b11111111111100000000011111100000 +
b11111110000000000000000011100011 $
b11111110000000000000000011100011 (
b11111111111111111111111111100000 /
b11111110000000000000000011100011 1
b110 &
b1000000 "
#14000
b10010001101000101000000000000 !
b10010001101000101000000000000 .
b100100011 ,
b100100000 *
b100100000 -
b10010001101000101000000000000 )
b1000101100100100010 +
b11 #
b11 '
b10010001101000101000000000000 $
b10010001101000101000000000000 (
b10010001101000101000000000000 /
b11 0
b10010001101000101000000000000 1
b111 &
b11111111111111111111111111100000 "
#16000
b11111111111111111111000000000000 !
b11111111111111111111000000000000 .
b11111111111111111111111111111111 ,
b11111111111111111111111111100000 *
b11111111111111111111011111100000 -
b11111111111111111111000000000000 )
b11111111111111111111111111111110 +
b11111111111111111111000000000000 $
b11111111111111111111000000000000 (
b11111111111111111111000000000000 /
b11111111111111111111000000000000 1
b1000 &
b10010001101000101000000000000 "
#18000
b100 !
b100 .
b100 ,
b1 *
b100000000000 -
b10000000000000000000000 )
b100 +
b100 #
b100 '
b10000000000000011101111 $
b10000000000000011101111 (
b100 /
b100 0
b10000000000000011101111 1
b1001 &
b11111111111111111111000000000000 "
#20000
b11111111111111111111100000000000 !
b11111111111111111111100000000000 .
b11111111111111111111100000000001 ,
b11111111111111111111100000000000 *
b11111111111111111111000000000000 -
b10000000000111111111000000000000 )
b11111111111111111111100000000000 +
b10000000000111111111000001101111 $
b10000000000111111111000001101111 (
b11111111111111111111100000000000 /
b10000000000111111111000001101111 1
b1010 &
b100 "
#22000
b1011 &
b11111111111111111111100000000000 "
