src/instr_slicer.v
`timescale 1ns / 1ps

module instr_slicer (
    input wire [31:0] instr,

    output wire [6:0] opcode,  // instr[6:0]
    output wire [4:0] rd,      // instr[11:7]
    output wire [2:0] funct3,  // instr[14:12]
    output wire [4:0] rs1,     // instr[19:15]
    output wire [4:0] rs2,     // instr[24:20] (R/S/B types)
    output wire [6:0] funct7,  // instr[31:25] (R type)

    output wire [ 4:0] shamt,  // instr[24:20] (I-type shifts: SLLI/SRLI/SRAI)
    output wire [19:0] csr     // instr[31:20] (SYSTEM/CSR)
);
  assign opcode = instr[6:0];
  assign rd     = instr[11:7];
  assign funct3 = instr[14:12];
  assign rs1    = instr[19:15];
  assign rs2    = instr[24:20];
  assign funct7 = instr[31:25];

  // Convenience
  assign shamt  = instr[24:20];
  assign csr    = instr[31:20];
endmodule

tb/instr_slicer_tb.v
`timescale 1ns / 1ps

// Verilog-2001 friendly ASSERT macro (no SystemVerilog assert/$error/$fatal)
`define CHECK(X) \
  if (!(X)) begin \
    $display("ASSERT FAILED: %s  instr=0x%08h  t=%0t", `"X`", instr, $time); \
    failed = failed + 1; \
  end else begin \
    passed = passed + 1; \
  end

module instr_slicer_tb;

  // DUT I/O
  reg [31:0] instr;
  wire [6:0] opcode, funct7;
  wire [4:0] rd, rs1, rs2, shamt;
  wire [ 2:0] funct3;
  wire [19:0] csr;

  // DUT
  instr_slicer dut (
      .instr (instr),
      .opcode(opcode),
      .rd    (rd),
      .funct3(funct3),
      .rs1   (rs1),
      .rs2   (rs2),
      .funct7(funct7),
      .shamt (shamt),
      .csr   (csr)
  );

  integer failed, passed;

  // Encoders (Verilog-2001: no 'automatic')
  function [31:0] enc_r;
    input [6:0] f7;
    input [4:0] r2, r1;
    input [2:0] f3;
    input [4:0] rd_;
    input [6:0] opc;
    begin
      enc_r = {f7, r2, r1, f3, rd_, opc};
    end
  endfunction

  function [31:0] enc_i;
    input [11:0] imm12;
    input [4:0] r1;
    input [2:0] f3;
    input [4:0] rd_;
    input [6:0] opc;
    begin
      enc_i = {imm12, r1, f3, rd_, opc};
    end
  endfunction

  function [31:0] enc_s;
    input [11:0] imm12;
    input [4:0] r2, r1;
    input [2:0] f3;
    input [6:0] opc;
    begin
      enc_s = {imm12[11:5], r2, r1, f3, imm12[4:0], opc};
    end
  endfunction

  function [31:0] enc_b;
    input [12:0] off;  // off[0] implied 0 in HW; placed per RISC-V B-type
    input [4:0] r2, r1;
    input [2:0] f3;
    input [6:0] opc;
    begin
      enc_b = {off[12], off[10:5], r2, r1, f3, off[4:1], off[11], opc};
    end
  endfunction

  function [31:0] enc_u;
    input [19:0] imm20;
    input [4:0] rd_;
    input [6:0] opc;
    begin
      enc_u = {imm20, rd_, opc};
    end
  endfunction

  function [31:0] enc_j;
    input [20:0] off;  // off[0] implied 0 in HW
    input [4:0] rd_;
    input [6:0] opc;
    begin
      enc_j = {off[20], off[10:1], off[11], off[19:12], rd_, opc};
    end
  endfunction

  task check_raw_bits;
    begin
      #1;
      `CHECK(opcode == instr[6:0])
      `CHECK(rd == instr[11:7])
      `CHECK(funct3 == instr[14:12])
      `CHECK(rs1 == instr[19:15])
      `CHECK(rs2 == instr[24:20])
      `CHECK(funct7 == instr[31:25])
      `CHECK(shamt == instr[24:20])
      `CHECK(csr == instr[31:20])
    end
  endtask

  integer i;

  initial begin
    $dumpfile("dump.vcd");
    $dumpvars(0, instr_slicer_tb);

    failed = 0;
    passed = 0;

    // R-type (e.g., SUB shape)
    instr  = enc_r(7'h20, 5'd3, 5'd2, 3'h0, 5'd1, 7'h33);
    check_raw_bits();

    // I-type (ADDI shape)
    instr = enc_i(12'h4a5, 5'd8, 3'h2, 5'd9, 7'h13);
    check_raw_bits();

    // I-type shift (SRLI/SRAI shape -> shamt tap)
    instr = enc_i({7'h00, 5'd12}, 5'd1, 3'h5, 5'd7, 7'h13);  // imm[11:5]=0, shamt=12
    check_raw_bits();
    `CHECK(shamt == 5'd12)

    // S-type (SW shape)
    instr = enc_s(12'h2b6, 5'd7, 5'd6, 3'h2, 7'h23);
    check_raw_bits();

    // B-type (BEQ shape)
    instr = enc_b(13'h1A2, 5'd11, 5'd10, 3'h0, 7'h63);
    check_raw_bits();

    // U-type (LUI shape)
    instr = enc_u(20'h12345, 5'd1, 7'h37);
    check_raw_bits();

    // J-type (JAL shape)
    instr = enc_j(21'h1_E7AD, 5'd5, 7'h6f);
    check_raw_bits();

    // SYSTEM/CSR (opcode 0x73): test csr tap
    instr = enc_i(12'habc, 5'd3, 3'h1, 5'd4, 7'h73);
    check_raw_bits();
    `CHECK(csr == 20'h0abc)  // csr is instr[31:20]

    // Edge patterns
    instr = 32'h0000_0000;
    check_raw_bits();
    instr = 32'hFFFF_FFFF;
    check_raw_bits();

    // Randomized smoke (Verilog: use $random instead of $urandom)
    for (i = 0; i < 200; i = i + 1) begin
      instr = $random;
      check_raw_bits();
    end

    if (failed == 0) $display("All instr_slicer assertions PASSED.");
    else $display("instr_slicer assertions FAILED: %0d failures, %0d passes.", failed, passed);

    $finish;
  end

endmodule

waves/instr_slicer.vcd
$date
	Tue Aug 26 13:29:42 2025
$end
$version
	Icarus Verilog
$end
$timescale
	1ps
$end
$scope module instr_slicer_tb $end
$var wire 5 ! shamt [4:0] $end
$var wire 5 " rs2 [4:0] $end
$var wire 5 # rs1 [4:0] $end
$var wire 5 $ rd [4:0] $end
$var wire 7 % opcode [6:0] $end
$var wire 7 & funct7 [6:0] $end
$var wire 3 ' funct3 [2:0] $end
$var wire 20 ( csr [19:0] $end
$var reg 32 ) instr [31:0] $end
$var integer 32 * failed [31:0] $end
$var integer 32 + i [31:0] $end
$var integer 32 , passed [31:0] $end
$scope function enc_b $end
$var reg 3 - f3 [2:0] $end
$var reg 13 . off [12:0] $end
$var reg 7 / opc [6:0] $end
$var reg 5 0 r1 [4:0] $end
$var reg 5 1 r2 [4:0] $end
$upscope $end
$scope function enc_i $end
$var reg 3 2 f3 [2:0] $end
$var reg 12 3 imm12 [11:0] $end
$var reg 7 4 opc [6:0] $end
$var reg 5 5 r1 [4:0] $end
$var reg 5 6 rd_ [4:0] $end
$upscope $end
$scope function enc_j $end
$var reg 21 7 off [20:0] $end
$var reg 7 8 opc [6:0] $end
$var reg 5 9 rd_ [4:0] $end
$upscope $end
$scope function enc_r $end
$var reg 3 : f3 [2:0] $end
$var reg 7 ; f7 [6:0] $end
$var reg 7 < opc [6:0] $end
$var reg 5 = r1 [4:0] $end
$var reg 5 > r2 [4:0] $end
$var reg 5 ? rd_ [4:0] $end
$upscope $end
$scope function enc_s $end
$var reg 3 @ f3 [2:0] $end
$var reg 12 A imm12 [11:0] $end
$var reg 7 B opc [6:0] $end
$var reg 5 C r1 [4:0] $end
$var reg 5 D r2 [4:0] $end
$upscope $end
$scope function enc_u $end
$var reg 20 E imm20 [19:0] $end
$var reg 7 F opc [6:0] $end
$var reg 5 G rd_ [4:0] $end
$upscope $end
$scope module dut $end
$var wire 32 H instr [31:0] $end
$var wire 5 I shamt [4:0] $end
$var wire 5 J rs2 [4:0] $end
$var wire 5 K rs1 [4:0] $end
$var wire 5 L rd [4:0] $end
$var wire 7 M opcode [6:0] $end
$var wire 7 N funct7 [6:0] $end
$var wire 3 O funct3 [2:0] $end
$var wire 20 P csr [19:0] $end
$upscope $end
$scope task check_raw_bits $end
$upscope $end
$upscope $end
$enddefinitions $end
$comment Show the parameter values. $end
$dumpall
$end
#0
$dumpvars
b10000000011 P
b0 O
b100000 N
b110011 M
b1 L
b10 K
b11 J
b11 I
b1000000001100010000000010110011 H
bx G
bx F
bx E
bx D
bx C
bx B
bx A
bx @
b1 ?
b11 >
b10 =
b110011 <
b100000 ;
b0 :
bx 9
bx 8
bx 7
bx 6
bx 5
bx 4
bx 3
bx 2
bx 1
bx 0
bx /
bx .
bx -
b0 ,
bx +
b0 *
b1000000001100010000000010110011 )
b10000000011 (
b0 '
b100000 &
b110011 %
b1 $
b10 #
b11 "
b11 !
$end
#1000
b10011 %
b10011 M
b1001 $
b1001 L
b10 '
b10 O
b1000 #
b1000 K
b101 "
b101 J
b100101 &
b100101 N
b101 !
b101 I
b10010100101 (
b10010100101 P
b1001010010101000010010010010011 )
b1001010010101000010010010010011 H
b10010100101 3
b1000 5
b10 2
b1001 6
b10011 4
b1000 ,
#2000
b111 $
b111 L
b101 '
b101 O
b1 #
b1 K
b1100 "
b1100 J
b0 &
b0 N
b1100 !
b1100 I
b1100 (
b1100 P
b110000001101001110010011 )
b110000001101001110010011 H
b1100 3
b1 5
b101 2
b111 6
b10000 ,
#3000
b100011 %
b100011 M
b10110 $
b10110 L
b10 '
b10 O
b110 #
b110 K
b111 "
b111 J
b10101 &
b10101 N
b111 !
b111 I
b1010100111 (
b1010100111 P
b101010011100110010101100100011 )
b101010011100110010101100100011 H
b1010110110 A
b111 D
b110 C
b10 @
b100011 B
b11001 ,
#4000
b1100011 %
b1100011 M
b10 $
b10 L
b0 '
b0 O
b1010 #
b1010 K
b1011 "
b1011 J
b1101 &
b1101 N
b1011 !
b1011 I
b110101011 (
b110101011 P
b11010101101010000000101100011 )
b11010101101010000000101100011 H
b110100010 .
b1011 1
b1010 0
b0 -
b1100011 /
b100001 ,
#5000
b110111 %
b110111 M
b1 $
b1 L
b101 '
b101 O
b1000 #
b1000 K
b11 "
b11 J
b1001 &
b1001 N
b11 !
b11 I
b100100011 (
b100100011 P
b10010001101000101000010110111 )
b10010001101000101000010110111 H
b10010001101000101 E
b1 G
b110111 F
b101001 ,
#6000
b1101111 %
b1101111 M
b101 $
b101 L
b110 '
b110 O
b11 #
b11 K
b1100 "
b1100 J
b111101 &
b111101 N
b1100 !
b1100 I
b11110101100 (
b11110101100 P
b1111010110000011110001011101111 )
b1111010110000011110001011101111 H
b11110011110101101 7
b101 9
b1101111 8
b110001 ,
#7000
b1110011 %
b1110011 M
b100 $
b100 L
b1 '
b1 O
b11100 "
b11100 J
b1010101 &
b1010101 N
b11100 !
b11100 I
b101010111100 (
b101010111100 P
b10101011110000011001001001110011 )
b10101011110000011001001001110011 H
b101010111100 3
b11 5
b1 2
b100 6
b1110011 4
b111001 ,
#8000
b0 %
b0 M
b0 $
b0 L
b0 '
b0 O
b0 #
b0 K
b0 "
b0 J
b0 &
b0 N
b0 !
b0 I
b0 (
b0 P
b0 )
b0 H
b1000010 ,
#9000
b1111111 %
b1111111 M
b11111 $
b11111 L
b111 '
b111 O
b11111 #
b11111 K
b11111 "
b11111 J
b1111111 &
b1111111 N
b11111 !
b11111 I
b111111111111 (
b111111111111 P
b11111111111111111111111111111111 )
b11111111111111111111111111111111 H
b1001010 ,
#10000
b100100 %
b100100 M
b1010 $
b1010 L
b11 '
b11 O
b1010 #
b1010 K
b1 "
b1 J
b1001 &
b1001 N
b1 !
b1 I
b100100001 (
b100100001 P
b10010000101010011010100100100 )
b10010000101010011010100100100 H
b0 +
b1010010 ,
#11000
b1 %
b1 M
b11101 $
b11101 L
b101 '
b101 O
b10010 #
b10010 K
b1000 "
b1000 J
b1100000 &
b1100000 N
b1000 !
b1000 I
b110000001000 (
b110000001000 P
b11000000100010010101111010000001 )
b11000000100010010101111010000001 H
b1 +
b1011010 ,
#12000
b1001 %
b1001 M
b1100 $
b1100 L
b1001 #
b1001 K
b1000010 &
b1000010 N
b100001001000 (
b100001001000 P
b10000100100001001101011000001001 )
b10000100100001001101011000001001 H
b10 +
b1100010 ,
#13000
b1100011 %
b1100011 M
b0 #
b0 K
b11111 "
b11111 J
b1011000 &
b1011000 N
b11111 !
b11111 I
b101100011111 (
b101100011111 P
b10110001111100000101011001100011 )
b10110001111100000101011001100011 H
b11 +
b1101010 ,
#14000
b1101 %
b1101 M
b10110 $
b10110 L
b111 '
b111 O
b10010 #
b10010 K
b1011 "
b1011 J
b11 &
b11 N
b1011 !
b1011 I
b1101011 (
b1101011 P
b110101110010111101100001101 )
b110101110010111101100001101 H
b100 +
b1110010 ,
#15000
b10011 $
b10011 L
b1 '
b1 O
b11111 #
b11111 K
b1101 "
b1101 J
b100011 &
b100011 N
b1101 !
b1101 I
b10001101101 (
b10001101101 P
b1000110110111111001100110001101 )
b1000110110111111001100110001101 H
b101 +
b1111010 ,
#16000
b1100101 %
b1100101 M
b1000 $
b1000 L
b0 '
b0 O
b101 #
b101 K
b1100 "
b1100 J
b1011001 &
b1011001 N
b1100 !
b1100 I
b101100101100 (
b101100101100 P
b10110010110000101000010001100101 )
b10110010110000101000010001100101 H
b110 +
b10000010 ,
#17000
b10010 %
b10010 M
b100 $
b100 L
b101 '
b101 O
b1110 #
b1110 K
b10011 "
b10011 J
b1000100 &
b1000100 N
b10011 !
b10011 I
b100010010011 (
b100010010011 P
b10001001001101110101001000010010 )
b10001001001101110101001000010010 H
b111 +
b10001010 ,
#18000
b1 %
b1 M
b110 $
b110 L
b110 '
b110 O
b111 #
b111 K
b1111 "
b1111 J
b0 &
b0 N
b1111 !
b1111 I
b1111 (
b1111 P
b111100111110001100000001 )
b111100111110001100000001 H
b1000 +
b10010010 ,
#19000
b1101 %
b1101 M
b11010 $
b11010 L
b100 '
b100 O
b1111 #
b1111 K
b1101 "
b1101 J
b11 &
b11 N
b1101 !
b1101 I
b1101101 (
b1101101 P
b110110101111100110100001101 )
b110110101111100110100001101 H
b1001 +
b10011010 ,
#20000
b1110110 %
b1110110 M
b10 $
b10 L
b111 '
b111 O
b111 #
b111 K
b10010 "
b10010 J
b11101 &
b11101 N
b10010 !
b10010 I
b1110110010 (
b1110110010 P
b111011001000111111000101110110 )
b111011001000111111000101110110 H
b1010 +
b10100010 ,
#21000
b111101 %
b111101 M
b11010 $
b11010 L
b100 '
b100 O
b11011 #
b11011 K
b1000 "
b1000 J
b1111 &
b1111 N
b1000 !
b1000 I
b111101000 (
b111101000 P
b11110100011011100110100111101 )
b11110100011011100110100111101 H
b1011 +
b10101010 ,
#22000
b1101101 %
b1101101 M
b1111 $
b1111 L
b101 '
b101 O
b1000 #
b1000 K
b1101 "
b1101 J
b111011 &
b111011 N
b1101 !
b1101 I
b11101101101 (
b11101101101 P
b1110110110101000101011111101101 )
b1110110110101000101011111101101 H
b1100 +
b10110010 ,
#23000
b1100 %
b1100 M
b111 '
b111 O
b11011 #
b11011 K
b10 "
b10 J
b100011 &
b100011 N
b10 !
b10 I
b10001100010 (
b10001100010 P
b1000110001011011111011110001100 )
b1000110001011011111011110001100 H
b1101 +
b10111010 ,
#24000
b1111001 %
b1111001 M
b10011 $
b10011 L
b110 '
b110 O
b1111 "
b1111 J
b111110 &
b111110 N
b1111 !
b1111 I
b11111001111 (
b11111001111 P
b1111100111111011110100111111001 )
b1111100111111011110100111111001 H
b1110 +
b11000010 ,
#25000
b1000110 %
b1000110 M
b1001 $
b1001 L
b10 '
b10 O
b1110 #
b1110 K
b10011 "
b10011 J
b1110001 &
b1110001 N
b10011 !
b10011 I
b111000110011 (
b111000110011 P
b11100011001101110010010011000110 )
b11100011001101110010010011000110 H
b1111 +
b11001010 ,
#26000
b1000101 %
b1000101 M
b0 '
b0 O
b1111 #
b1111 K
b1111 "
b1111 J
b1111 !
b1111 I
b111000101111 (
b111000101111 P
b11100010111101111000010011000101 )
b11100010111101111000010011000101 H
b10000 +
b11010010 ,
#27000
b101010 %
b101010 M
b101 $
b101 L
b101 '
b101 O
b111 #
b111 K
b10001 "
b10001 J
b1101010 &
b1101010 N
b10001 !
b10001 I
b110101010001 (
b110101010001 P
b11010101000100111101001010101010 )
b11010101000100111101001010101010 H
b10001 +
b11011010 ,
#28000
b1100101 %
b1100101 M
b1111 $
b1111 L
b111 '
b111 O
b11111 #
b11111 K
b1010 "
b1010 J
b111001 &
b111001 N
b1010 !
b1010 I
b11100101010 (
b11100101010 P
b1110010101011111111011111100101 )
b1110010101011111111011111100101 H
b10010 +
b11100010 ,
#29000
b1110111 %
b1110111 M
b100 $
b100 L
b100 #
b100 K
b11101 "
b11101 J
b1011101 &
b1011101 N
b11101 !
b11101 I
b101110111101 (
b101110111101 P
b10111011110100100111001001110111 )
b10111011110100100111001001110111 H
b10011 +
b11101010 ,
#30000
b10010 %
b10010 M
b1100 $
b1100 L
b101 '
b101 O
b101 #
b101 K
b10011 "
b10011 J
b1000100 &
b1000100 N
b10011 !
b10011 I
b100010010011 (
b100010010011 P
b10001001001100101101011000010010 )
b10001001001100101101011000010010 H
b10100 +
b11110010 ,
#31000
b1111 %
b1111 M
b10111 $
b10111 L
b11001 #
b11001 K
b11110 "
b11110 J
b100011 &
b100011 N
b11110 !
b11110 I
b10001111110 (
b10001111110 P
b1000111111011001101101110001111 )
b1000111111011001101101110001111 H
b10101 +
b11111010 ,
#32000
b1110010 %
b1110010 M
b10011 $
b10011 L
b110 '
b110 O
b0 #
b0 K
b10011 "
b10011 J
b111100 &
b111100 N
b10011 !
b10011 I
b11110010011 (
b11110010011 P
b1111001001100000110100111110010 )
b1111001001100000110100111110010 H
b10110 +
b100000010 ,
#33000
b1001110 %
b1001110 M
b1101 $
b1101 L
b1 '
b1 O
b1101 #
b1101 K
b10111 "
b10111 J
b1110011 &
b1110011 N
b10111 !
b10111 I
b111001110111 (
b111001110111 P
b11100111011101101001011011001110 )
b11100111011101101001011011001110 H
b10111 +
b100001010 ,
#34000
b1101000 %
b1101000 M
b10101 $
b10101 L
b111 '
b111 O
b0 #
b0 K
b0 "
b0 J
b1111010 &
b1111010 N
b0 !
b0 I
b111101000000 (
b111101000000 P
b11110100000000000111101011101000 )
b11110100000000000111101011101000 H
b11000 +
b100010010 ,
#35000
b1000101 %
b1000101 M
b11101 $
b11101 L
b100 '
b100 O
b10100 #
b10100 K
b1100 "
b1100 J
b1110001 &
b1110001 N
b1100 !
b1100 I
b111000101100 (
b111000101100 P
b11100010110010100100111011000101 )
b11100010110010100100111011000101 H
b11001 +
b100011010 ,
#36000
b1011100 %
b1011100 M
b10010 $
b10010 L
b10000 #
b10000 K
b101 "
b101 J
b10111 &
b10111 N
b101 !
b101 I
b1011100101 (
b1011100101 P
b101110010110000100100101011100 )
b101110010110000100100101011100 H
b11010 +
b100100010 ,
#37000
b111101 %
b111101 M
b10001 $
b10001 L
b10 '
b10 O
b11100 #
b11100 K
b1000 "
b1000 J
b1101111 &
b1101111 N
b1000 !
b1000 I
b110111101000 (
b110111101000 P
b11011110100011100010100010111101 )
b11011110100011100010100010111101 H
b11011 +
b100101010 ,
#38000
b101101 %
b101101 M
b10000 $
b10000 L
b101 '
b101 O
b10110 #
b10110 K
b1010 "
b1010 J
b1001011 &
b1001011 N
b1010 !
b1010 I
b100101101010 (
b100101101010 P
b10010110101010110101100000101101 )
b10010110101010110101100000101101 H
b11100 +
b100110010 ,
#39000
b1100101 %
b1100101 M
b1100 $
b1100 L
b10 '
b10 O
b1110 #
b1110 K
b1011001 &
b1011001 N
b101100101010 (
b101100101010 P
b10110010101001110010011001100101 )
b10110010101001110010011001100101 H
b11101 +
b100111010 ,
#40000
b1100011 %
b1100011 M
b100 $
b100 L
b110 '
b110 O
b11110 #
b11110 K
b11110 "
b11110 J
b1011000 &
b1011000 N
b11110 !
b11110 I
b101100011110 (
b101100011110 P
b10110001111011110110001001100011 )
b10110001111011110110001001100011 H
b11110 +
b101000010 ,
#41000
b1010 %
b1010 M
b1110 $
b1110 L
b0 '
b0 O
b111 #
b111 K
b10111 "
b10111 J
b10 &
b10 N
b10111 !
b10111 I
b1010111 (
b1010111 P
b101011100111000011100001010 )
b101011100111000011100001010 H
b11111 +
b101001010 ,
#42000
b0 %
b0 M
b101 $
b101 L
b10 '
b10 O
b10110 #
b10110 K
b11 "
b11 J
b1100000 &
b1100000 N
b11 !
b11 I
b110000000011 (
b110000000011 P
b11000000001110110010001010000000 )
b11000000001110110010001010000000 H
b100000 +
b101010010 ,
#43000
b100000 %
b100000 M
b10 $
b10 L
b1000 #
b1000 K
b110 "
b110 J
b1000 &
b1000 N
b110 !
b110 I
b100000110 (
b100000110 P
b10000011001000010000100100000 )
b10000011001000010000100100000 H
b100001 +
b101011010 ,
#44000
b101010 %
b101010 M
b1011 $
b1011 L
b100 '
b100 O
b10000 #
b10000 K
b10111 "
b10111 J
b101010 &
b101010 N
b10111 !
b10111 I
b10101010111 (
b10101010111 P
b1010101011110000100010110101010 )
b1010101011110000100010110101010 H
b100010 +
b101100010 ,
#45000
b11101 %
b11101 M
b11001 $
b11001 L
b11001 #
b11001 K
b1100 "
b1100 J
b1100111 &
b1100111 N
b1100 !
b1100 I
b110011101100 (
b110011101100 P
b11001110110011001100110010011101 )
b11001110110011001100110010011101 H
b100011 +
b101101010 ,
#46000
b10110 %
b10110 M
b11101 $
b11101 L
b11 '
b11 O
b0 #
b0 K
b10010 "
b10010 J
b1100101 &
b1100101 N
b10010 !
b10010 I
b110010110010 (
b110010110010 P
b11001011001000000011111010010110 )
b11001011001000000011111010010110 H
b100100 +
b101110010 ,
#47000
b10011 %
b10011 M
b10000 $
b10000 L
b111 #
b111 K
b11000 "
b11000 J
b1000100 &
b1000100 N
b11000 !
b11000 I
b100010011000 (
b100010011000 P
b10001001100000111011100000010011 )
b10001001100000111011100000010011 H
b100101 +
b101111010 ,
#48000
b1101 %
b1101 M
b11000 #
b11000 K
b1011 "
b1011 J
b1000011 &
b1000011 N
b1011 !
b1011 I
b100001101011 (
b100001101011 P
b10000110101111000011100000001101 )
b10000110101111000011100000001101 H
b100110 +
b110000010 ,
#49000
b1010011 %
b1010011 M
b1100 $
b1100 L
b101 '
b101 O
b1111 #
b1111 K
b11010 "
b11010 J
b1010100 &
b1010100 N
b11010 !
b11010 I
b101010011010 (
b101010011010 P
b10101001101001111101011001010011 )
b10101001101001111101011001010011 H
b100111 +
b110001010 ,
#50000
b1101011 %
b1101011 M
b11010 $
b11010 L
b11111 #
b11111 K
b11001 "
b11001 J
b11010 &
b11010 N
b11001 !
b11001 I
b1101011001 (
b1101011001 P
b110101100111111101110101101011 )
b110101100111111101110101101011 H
b101000 +
b110010010 ,
#51000
b1010101 %
b1010101 M
b10101 $
b10101 L
b10 '
b10 O
b1100 #
b1100 K
b1010 "
b1010 J
b1110101 &
b1110101 N
b1010 !
b1010 I
b111010101010 (
b111010101010 P
b11101010101001100010101011010101 )
b11101010101001100010101011010101 H
b101001 +
b110011010 ,
#52000
b10 %
b10 M
b10100 $
b10100 L
b100 '
b100 O
b1110 #
b1110 K
b10001 "
b10001 J
b1000000 &
b1000000 N
b10001 !
b10001 I
b100000010001 (
b100000010001 P
b10000001000101110100101000000010 )
b10000001000101110100101000000010 H
b101010 +
b110100010 ,
#53000
b101110 %
b101110 M
b11101 $
b11101 L
b11 '
b11 O
b1100 #
b1100 K
b10101 "
b10101 J
b1101011 &
b1101011 N
b10101 !
b10101 I
b110101110101 (
b110101110101 P
b11010111010101100011111010101110 )
b11010111010101100011111010101110 H
b101011 +
b110101010 ,
#54000
b11101 %
b11101 M
b10010 $
b10010 L
b110 '
b110 O
b11111 #
b11111 K
b1111 "
b1111 J
b111 &
b111 N
b1111 !
b1111 I
b11101111 (
b11101111 P
b1110111111111110100100011101 )
b1110111111111110100100011101 H
b101100 +
b110110010 ,
#55000
b1001111 %
b1001111 M
b101 $
b101 L
b111 '
b111 O
b1010 #
b1010 K
b11100 "
b11100 J
b1110011 &
b1110011 N
b11100 !
b11100 I
b111001111100 (
b111001111100 P
b11100111110001010111001011001111 )
b11100111110001010111001011001111 H
b101101 +
b110111010 ,
#56000
b100011 %
b100011 M
b10010 $
b10010 L
b100 '
b100 O
b1000 #
b1000 K
b11000 "
b11000 J
b1000 &
b1000 N
b11000 !
b11000 I
b100011000 (
b100011000 P
b10001100001000100100100100011 )
b10001100001000100100100100011 H
b101110 +
b111000010 ,
#57000
b1010 %
b1010 M
b1010 $
b1010 L
b110 '
b110 O
b10010 #
b10010 K
b10000 "
b10000 J
b10 &
b10 N
b10000 !
b10000 I
b1010000 (
b1010000 P
b101000010010110010100001010 )
b101000010010110010100001010 H
b101111 +
b111001010 ,
#58000
b1001010 %
b1001010 M
b10101 $
b10101 L
b0 '
b0 O
b110 #
b110 K
b10111 "
b10111 J
b1110010 &
b1110010 N
b10111 !
b10111 I
b111001010111 (
b111001010111 P
b11100101011100110000101011001010 )
b11100101011100110000101011001010 H
b110000 +
b111010010 ,
#59000
b111100 %
b111100 M
b11000 $
b11000 L
b100 '
b100 O
b10 #
b10 K
b11 "
b11 J
b1001111 &
b1001111 N
b11 !
b11 I
b100111100011 (
b100111100011 P
b10011110001100010100110000111100 )
b10011110001100010100110000111100 H
b110001 +
b111011010 ,
#60000
b1110010 %
b1110010 M
b11011 $
b11011 L
b11 '
b11 O
b10001 #
b10001 K
b10110 "
b10110 J
b111100 &
b111100 N
b10110 !
b10110 I
b11110010110 (
b11110010110 P
b1111001011010001011110111110010 )
b1111001011010001011110111110010 H
b110010 +
b111100010 ,
#61000
b1010 %
b1010 M
b11 $
b11 L
b110 '
b110 O
b11100 #
b11100 K
b10010 "
b10010 J
b100010 &
b100010 N
b10010 !
b10010 I
b10001010010 (
b10001010010 P
b1000101001011100110000110001010 )
b1000101001011100110000110001010 H
b110011 +
b111101010 ,
#62000
b1000001 %
b1000001 M
b110 $
b110 L
b11 '
b11 O
b1001 #
b1001 K
b1100 "
b1100 J
b10000 &
b10000 N
b1100 !
b1100 I
b1000001100 (
b1000001100 P
b100000110001001011001101000001 )
b100000110001001011001101000001 H
b110100 +
b111110010 ,
#63000
b1011000 %
b1011000 M
b1001 $
b1001 L
b10110 #
b10110 K
b100 "
b100 J
b1110110 &
b1110110 N
b100 !
b100 I
b111011000100 (
b111011000100 P
b11101100010010110011010011011000 )
b11101100010010110011010011011000 H
b110101 +
b111111010 ,
#64000
b1111000 %
b1111000 M
b110 $
b110 L
b111 '
b111 O
b1 #
b1 K
b10 "
b10 J
b11110 &
b11110 N
b10 !
b10 I
b1111000010 (
b1111000010 P
b111100001000001111001101111000 )
b111100001000001111001101111000 H
b110110 +
b1000000010 ,
#65000
b1001 %
b1001 M
b101 $
b101 L
b1 '
b1 O
b10100 #
b10100 K
b1000 "
b1000 J
b1100010 &
b1100010 N
b1000 !
b1000 I
b110001001000 (
b110001001000 P
b11000100100010100001001010001001 )
b11000100100010100001001010001001 H
b110111 +
b1000001010 ,
#66000
b1101011 %
b1101011 M
b11011 $
b11011 L
b0 '
b0 O
b1010 #
b1010 K
b11100 "
b11100 J
b111010 &
b111010 N
b11100 !
b11100 I
b11101011100 (
b11101011100 P
b1110101110001010000110111101011 )
b1110101110001010000110111101011 H
b111000 +
b1000010010 ,
#67000
b110110 %
b110110 M
b1011 $
b1011 L
b110 '
b110 O
b100 #
b100 K
b10000 "
b10000 J
b101101 &
b101101 N
b10000 !
b10000 I
b10110110000 (
b10110110000 P
b1011011000000100110010110110110 )
b1011011000000100110010110110110 H
b111001 +
b1000011010 ,
#68000
b1000110 %
b1000110 M
b10011 $
b10011 L
b111 '
b111 O
b10111 #
b10111 K
b10100 "
b10100 J
b110001 &
b110001 N
b10100 !
b10100 I
b11000110100 (
b11000110100 P
b1100011010010111111100111000110 )
b1100011010010111111100111000110 H
b111010 +
b1000100010 ,
#69000
b101110 %
b101110 M
b111 $
b111 L
b1 '
b1 O
b1010 #
b1010 K
b10001 "
b10001 J
b101011 &
b101011 N
b10001 !
b10001 I
b10101110001 (
b10101110001 P
b1010111000101010001001110101110 )
b1010111000101010001001110101110 H
b111011 +
b1000101010 ,
#70000
b111100 %
b111100 M
b101 $
b101 L
b0 '
b0 O
b111 "
b111 J
b1101111 &
b1101111 N
b111 !
b111 I
b110111100111 (
b110111100111 P
b11011110011101010000001010111100 )
b11011110011101010000001010111100 H
b111100 +
b1000110010 ,
#71000
b101010 %
b101010 M
b11010 $
b11010 L
b101 '
b101 O
b11111 #
b11111 K
b10000 "
b10000 J
b1010 &
b1010 N
b10000 !
b10000 I
b101010000 (
b101010000 P
b10101000011111101110100101010 )
b10101000011111101110100101010 H
b111101 +
b1000111010 ,
#72000
b1011 %
b1011 M
b10100 $
b10100 L
b1 '
b1 O
b1111 #
b1111 K
b11101 "
b11101 J
b1000010 &
b1000010 N
b11101 !
b11101 I
b100001011101 (
b100001011101 P
b10000101110101111001101000001011 )
b10000101110101111001101000001011 H
b111110 +
b1001000010 ,
#73000
b1110001 %
b1110001 M
b11100 $
b11100 L
b11 '
b11 O
b1001 "
b1001 J
b1011100 &
b1011100 N
b1001 !
b1001 I
b101110001001 (
b101110001001 P
b10111000100101111011111001110001 )
b10111000100101111011111001110001 H
b111111 +
b1001001010 ,
#74000
b101 %
b101 M
b11 $
b11 L
b100 '
b100 O
b100 #
b100 K
b1111 "
b1111 J
b100001 &
b100001 N
b1111 !
b1111 I
b10000101111 (
b10000101111 P
b1000010111100100100000110000101 )
b1000010111100100100000110000101 H
b1000000 +
b1001010010 ,
#75000
b1001111 %
b1001111 M
b1010 $
b1010 L
b101 '
b101 O
b11111 "
b11111 J
b10011 &
b10011 N
b11111 !
b11111 I
b1001111111 (
b1001111111 P
b100111111100100101010101001111 )
b100111111100100101010101001111 H
b1000001 +
b1001011010 ,
#76000
b111011 %
b111011 M
b0 $
b0 L
b110 '
b110 O
b11000 #
b11000 K
b11100 "
b11100 J
b1001110 &
b1001110 N
b11100 !
b11100 I
b100111011100 (
b100111011100 P
b10011101110011000110000000111011 )
b10011101110011000110000000111011 H
b1000010 +
b1001100010 ,
#77000
b111010 %
b111010 M
b110 $
b110 L
b11 '
b11 O
b1100 #
b1100 K
b10000 "
b10000 J
b1110 &
b1110 N
b10000 !
b10000 I
b111010000 (
b111010000 P
b11101000001100011001100111010 )
b11101000001100011001100111010 H
b1000011 +
b1001101010 ,
