src/pc.v
// pc.v
module pc (
    input  wire        clk,        // Clock signal
    input  wire        reset,      // Asynchronous reset, active high
    input  wire [31:0] next_pc,    // Next PC value (from adder/MUX)
    output reg  [31:0] current_pc  // Holds the current PC value
);

  // On the rising edge of clk or an asserted reset...
  always @(posedge clk or posedge reset) begin
    if (reset) 
      current_pc <= 32'b0;        // Initialize PC to 0 after reset
    else
      current_pc <= next_pc;      // Otherwise, load next_pc
  end

endmodule

tb/pc_tb.v

`timescale 1ns / 1ps

module pc_tb;
  // Inputs to DUT
  reg         clk;
  reg         reset;
  reg  [31:0] next_pc;
  // Output from DUT
  wire [31:0] current_pc;

  // Instantiate the PC module (Device Under Test)
  pc uut (
      .clk       (clk),
      .reset     (reset),
      .next_pc   (next_pc),
      .current_pc(current_pc)
  );

  // 1) Clock generator: 10 ns period (100 MHz)
  initial clk = 0;
  always #5 clk = ~clk;

  // 2) Stimulus
  initial begin
    $dumpfile("dump.vcd");
    $dumpvars(0, pc_tb);

    // Print header
    $display("Time\t reset next_pc    current_pc");
    $monitor("%0dns\t   %b    %h    %h", $time, reset, next_pc, current_pc);

    // --- 2a) Reset the PC ---
    reset   = 1;
    next_pc = 32'h00000000;
    #10;  // wait one clock
    reset = 0;

    // After reset, current_pc should be 0
    #10;

    // --- 2b) Sequential increments ---
    // Feed next_pc = PC+4
    next_pc = 32'h00000004;
    #10;
    next_pc = 32'h00000008;
    #10;

    // --- 2c) Branch target test ---
    next_pc = 32'h000000A0;
    #10;

    // Finish simulation
    #10;
    $finish;
  end

endmodule

waves/pc.vcd
$date
	Tue Aug 26 13:29:42 2025
$end
$version
	Icarus Verilog
$end
$timescale
	1ps
$end
$scope module pc_tb $end
$var wire 32 ! current_pc [31:0] $end
$var reg 1 " clk $end
$var reg 32 # next_pc [31:0] $end
$var reg 1 $ reset $end
$scope module uut $end
$var wire 1 " clk $end
$var wire 32 % next_pc [31:0] $end
$var wire 1 $ reset $end
$var reg 32 & current_pc [31:0] $end
$upscope $end
$upscope $end
$enddefinitions $end
$comment Show the parameter values. $end
$dumpall
$end
#0
$dumpvars
b0 &
b0 %
1$
b0 #
0"
b0 !
$end
#5000
1"
#10000
0"
0$
#15000
1"
#20000
0"
b100 #
b100 %
#25000
b100 !
b100 &
1"
#30000
0"
b1000 #
b1000 %
#35000
b1000 !
b1000 &
1"
#40000
0"
b10100000 #
b10100000 %
#45000
b10100000 !
b10100000 &
1"
