src/regfile.v
// regfile.v
// 32×32 register file with two read ports and one write port

module reg_file (
    input  wire        clk,         // clock
    input  wire        reset,       // active‐high synchronous reset
    input  wire        regwrite,    // write enable
    input  wire [4:0]  read_reg1,   // address of source register 1
    input  wire [4:0]  read_reg2,   // address of source register 2
    input  wire [4:0]  write_reg,   // address of destination register
    input  wire [31:0] write_data,  // data to write
    output wire [31:0] read_data1,  // data from source register 1
    output wire [31:0] read_data2   // data from source register 2
);

    // Register storage
    reg [31:0] regs [31:0];
    integer i;

    // Write logic (and optional reset)
    always @(posedge clk) begin
        if (reset) begin
            // clear all registers on reset
            for (i = 0; i < 32; i = i + 1)
                regs[i] <= 32'b0;
        end else if (regwrite && (write_reg != 5'd0)) begin
            // write to regs[write_reg]; skip register 0
            regs[write_reg] <= write_data;
        end
    end

    // Asynchronous read ports (register 0 always reads 0)
    assign read_data1 = (read_reg1 != 5'd0) ? regs[read_reg1] : 32'b0;
    assign read_data2 = (read_reg2 != 5'd0) ? regs[read_reg2] : 32'b0;

endmodule

tb/regfile_tb.v
`timescale 1ns/1ps

module regfile_tb;
    // Signals
    reg         clk;
    reg         reset;
    reg         regwrite;
    reg  [4:0]  read_reg1, read_reg2, write_reg;
    reg  [31:0] write_data;
    wire [31:0] read_data1, read_data2;

    // Golden model of the register file contents
    reg [31:0] expected [31:0];

    // Instantiate DUT
    reg_file uut (
        .clk        (clk),
        .reset      (reset),
        .regwrite   (regwrite),
        .read_reg1  (read_reg1),
        .read_reg2  (read_reg2),
        .write_reg  (write_reg),
        .write_data (write_data),
        .read_data1 (read_data1),
        .read_data2 (read_data2)
    );

    // Clock generator (10 ns period)
    initial clk = 0;
    always #5 clk = ~clk;

    // Write task: drives write port on next rising edge, updates golden model
    task writeReg(input [4:0] addr, input [31:0] data);
    begin
        // prepare for write
        @(negedge clk);
        regwrite   = 1;
        write_reg  = addr;
        write_data = data;
        // capture on posedge
        @(posedge clk);
        if (addr != 0)
            expected[addr] = data;
    end
    endtask

    // Read & check task: compares DUT’s outputs to golden model
    task readAndCheck(input [4:0] addr1,
                      input [4:0] addr2);
    reg [31:0] exp1, exp2;
    begin
        exp1 = expected[addr1];
        exp2 = expected[addr2];
        read_reg1 = addr1;
        read_reg2 = addr2;
        #1; // allow combinational read to settle
        if (read_data1 !== exp1)
          $display("ERROR: time=%0t READ1[%0d]=0x%08h (exp=0x%08h)",
                   $time, addr1, read_data1, exp1);
        else
          $display("PASS : time=%0t READ1[%0d]=0x%08h",
                   $time, addr1, read_data1);
        if (read_data2 !== exp2)
          $display("ERROR: time=%0t READ2[%0d]=0x%08h (exp=0x%08h)",
                   $time, addr2, read_data2, exp2);
        else
          $display("PASS : time=%0t READ2[%0d]=0x%08h",
                   $time, addr2, read_data2);
    end
    endtask

    integer i;
    reg [4:0] next_reg;

    initial begin
        // dump waveform
        $dumpfile("dump.vcd");
        $dumpvars(0, regfile_tb);

        // Initialize DUT signals
        reset      = 1;
        regwrite   = 0;
        read_reg1  = 0;
        read_reg2  = 0;
        write_reg  = 0;
        write_data = 0;
        // Initialize golden model to zeros
        for (i = 0; i < 32; i = i + 1)
            expected[i] = 32'd0;

        $display("\n===== Extended Register File Testbench =====\n");

        // 1) SYNCHRONOUS RESET TEST
        #12 reset = 0;  // hold reset through one rising edge
        #1;            // wait for async-read settle
        $display("-- After reset (all regs should be 0) --");
        for (i = 0; i < 32; i = i + 2)
            readAndCheck(i, i+1);

        // 2) ZERO-REGISTER PROTECTION
        $display("\n-- Attempt write to x0 (should remain 0) --");
        writeReg(5'd0, 32'hDEADBEEF);
        readAndCheck(5'd0, 5'd1);

        // 3) INDIVIDUAL WRITES 1–31
        $display("\n-- Write/read pattern to x1..x31 --");
        for (i = 1; i < 32; i = i + 1) begin
            writeReg(i, i * 32'h11111111);
            readAndCheck(i, 5'd0);
        end

        // 4) BACK‐TO‐BACK WRITES
        $display("\n-- Back‐to‐back writes to x5 and x10 --");
        writeReg(5'd5,  32'hAAAA0000);
        writeReg(5'd10, 32'h5555FFFF);
        readAndCheck(5'd5, 5'd10);

        // 5) RANDOMIZED STRESS TEST
        $display("\n-- Randomized writes & reads --");
        for (i = 0; i < 20; i = i + 1) begin
            next_reg = $urandom_range(0,31);
            writeReg(next_reg,
                     (next_reg==0) ? 32'h0 : $urandom);
            readAndCheck(next_reg, $urandom_range(0,31));
        end

        // 6) FINAL RESET
        $display("\n-- Assert reset again (all should clear) --");
        #5 reset = 1;
        @(posedge clk);
        reset = 0;
        #1;
        for (i = 0; i < 8; i = i + 1)
            readAndCheck(i, i+8);

        $display("\n===== Test Complete =====\n");
        #10 $finish;
    end
endmodule

waves/regfile.vcd
$date
	Sat Jun 28 20:38:17 2025
$end
$version
	Icarus Verilog
$end
$timescale
	1ps
$end
$scope module regfile_tb $end
$var wire 32 ! read_data2 [31:0] $end
$var wire 32 " read_data1 [31:0] $end
$var reg 1 # clk $end
$var reg 5 $ next_reg [4:0] $end
$var reg 5 % read_reg1 [4:0] $end
$var reg 5 & read_reg2 [4:0] $end
$var reg 1 ' regwrite $end
$var reg 1 ( reset $end
$var reg 32 ) write_data [31:0] $end
$var reg 5 * write_reg [4:0] $end
$var integer 32 + i [31:0] $end
$scope module uut $end
$var wire 1 # clk $end
$var wire 5 , read_reg1 [4:0] $end
$var wire 5 - read_reg2 [4:0] $end
$var wire 1 ' regwrite $end
$var wire 1 ( reset $end
$var wire 32 . write_data [31:0] $end
$var wire 5 / write_reg [4:0] $end
$var wire 32 0 read_data2 [31:0] $end
$var wire 32 1 read_data1 [31:0] $end
$var integer 32 2 i [31:0] $end
$upscope $end
$scope task readAndCheck $end
$var reg 5 3 addr1 [4:0] $end
$var reg 5 4 addr2 [4:0] $end
$var reg 32 5 exp1 [31:0] $end
$var reg 32 6 exp2 [31:0] $end
$upscope $end
$scope task writeReg $end
$var reg 5 7 addr [4:0] $end
$var reg 32 8 data [31:0] $end
$upscope $end
$upscope $end
$enddefinitions $end
$comment Show the parameter values. $end
$dumpall
$end
#0
$dumpvars
bx 8
bx 7
bx 6
bx 5
bx 4
bx 3
bx 2
b0 1
b0 0
b0 /
b0 .
b0 -
b0 ,
b100000 +
b0 *
b0 )
1(
0'
b0 &
b0 %
bx $
0#
b0 "
b0 !
$end
#5000
b100000 2
1#
#10000
0#
#12000
0(
#13000
b1 &
b1 -
b0 6
b0 5
b1 4
b0 3
b0 +
#14000
b11 &
b11 -
b10 %
b10 ,
b11 4
b10 3
b10 +
#15000
b101 &
b101 -
b100 %
b100 ,
b101 4
b100 3
b100 +
1#
#16000
b111 &
b111 -
b110 %
b110 ,
b111 4
b110 3
b110 +
#17000
b1001 &
b1001 -
b1000 %
b1000 ,
b1001 4
b1000 3
b1000 +
#18000
b1011 &
b1011 -
b1010 %
b1010 ,
b1011 4
b1010 3
b1010 +
#19000
b1101 &
b1101 -
b1100 %
b1100 ,
b1101 4
b1100 3
b1100 +
#20000
b1111 &
b1111 -
b1110 %
b1110 ,
b1111 4
b1110 3
b1110 +
0#
#21000
b10001 &
b10001 -
b10000 %
b10000 ,
b10001 4
b10000 3
b10000 +
#22000
b10011 &
b10011 -
b10010 %
b10010 ,
b10011 4
b10010 3
b10010 +
#23000
b10101 &
b10101 -
b10100 %
b10100 ,
b10101 4
b10100 3
b10100 +
#24000
b10111 &
b10111 -
b10110 %
b10110 ,
b10111 4
b10110 3
b10110 +
#25000
b11001 &
b11001 -
b11000 %
b11000 ,
b11001 4
b11000 3
b11000 +
1#
#26000
b11011 &
b11011 -
b11010 %
b11010 ,
b11011 4
b11010 3
b11010 +
#27000
b11101 &
b11101 -
b11100 %
b11100 ,
b11101 4
b11100 3
b11100 +
#28000
b11111 &
b11111 -
b11110 %
b11110 ,
b11111 4
b11110 3
b11110 +
#29000
b11011110101011011011111011101111 8
b0 7
b100000 +
#30000
b11011110101011011011111011101111 )
b11011110101011011011111011101111 .
1'
0#
#35000
b1 &
b1 -
b0 %
b0 ,
b1 4
b0 3
1#
#36000
b10001000100010001000100010001 8
b1 7
b1 +
#40000
b10001000100010001000100010001 )
b10001000100010001000100010001 .
b1 *
b1 /
0#
#45000
b10001000100010001000100010001 "
b10001000100010001000100010001 1
b0 &
b0 -
b1 %
b1 ,
b10001000100010001000100010001 5
b0 4
b1 3
1#
#46000
b100010001000100010001000100010 8
b10 7
b10 +
#50000
b100010001000100010001000100010 )
b100010001000100010001000100010 .
b10 *
b10 /
0#
#55000
b100010001000100010001000100010 "
b100010001000100010001000100010 1
b10 %
b10 ,
b100010001000100010001000100010 5
b10 3
1#
#56000
b110011001100110011001100110011 8
b11 7
b11 +
#60000
b110011001100110011001100110011 )
b110011001100110011001100110011 .
b11 *
b11 /
0#
#65000
b110011001100110011001100110011 "
b110011001100110011001100110011 1
b11 %
b11 ,
b110011001100110011001100110011 5
b11 3
1#
#66000
b1000100010001000100010001000100 8
b100 7
b100 +
#70000
b1000100010001000100010001000100 )
b1000100010001000100010001000100 .
b100 *
b100 /
0#
#75000
b1000100010001000100010001000100 "
b1000100010001000100010001000100 1
b100 %
b100 ,
b1000100010001000100010001000100 5
b100 3
1#
#76000
b1010101010101010101010101010101 8
b101 7
b101 +
#80000
b1010101010101010101010101010101 )
b1010101010101010101010101010101 .
b101 *
b101 /
0#
#85000
b1010101010101010101010101010101 "
b1010101010101010101010101010101 1
b101 %
b101 ,
b1010101010101010101010101010101 5
b101 3
1#
#86000
b1100110011001100110011001100110 8
b110 7
b110 +
#90000
b1100110011001100110011001100110 )
b1100110011001100110011001100110 .
b110 *
b110 /
0#
#95000
b1100110011001100110011001100110 "
b1100110011001100110011001100110 1
b110 %
b110 ,
b1100110011001100110011001100110 5
b110 3
1#
#96000
b1110111011101110111011101110111 8
b111 7
b111 +
#100000
b1110111011101110111011101110111 )
b1110111011101110111011101110111 .
b111 *
b111 /
0#
#105000
b1110111011101110111011101110111 "
b1110111011101110111011101110111 1
b111 %
b111 ,
b1110111011101110111011101110111 5
b111 3
1#
#106000
b10001000100010001000100010001000 8
b1000 7
b1000 +
#110000
b10001000100010001000100010001000 )
b10001000100010001000100010001000 .
b1000 *
b1000 /
0#
#115000
b10001000100010001000100010001000 "
b10001000100010001000100010001000 1
b1000 %
b1000 ,
b10001000100010001000100010001000 5
b1000 3
1#
#116000
b10011001100110011001100110011001 8
b1001 7
b1001 +
#120000
b10011001100110011001100110011001 )
b10011001100110011001100110011001 .
b1001 *
b1001 /
0#
#125000
b10011001100110011001100110011001 "
b10011001100110011001100110011001 1
b1001 %
b1001 ,
b10011001100110011001100110011001 5
b1001 3
1#
#126000
b10101010101010101010101010101010 8
b1010 7
b1010 +
#130000
b10101010101010101010101010101010 )
b10101010101010101010101010101010 .
b1010 *
b1010 /
0#
#135000
b10101010101010101010101010101010 "
b10101010101010101010101010101010 1
b1010 %
b1010 ,
b10101010101010101010101010101010 5
b1010 3
1#
#136000
b10111011101110111011101110111011 8
b1011 7
b1011 +
#140000
b10111011101110111011101110111011 )
b10111011101110111011101110111011 .
b1011 *
b1011 /
0#
#145000
b10111011101110111011101110111011 "
b10111011101110111011101110111011 1
b1011 %
b1011 ,
b10111011101110111011101110111011 5
b1011 3
1#
#146000
b11001100110011001100110011001100 8
b1100 7
b1100 +
#150000
b11001100110011001100110011001100 )
b11001100110011001100110011001100 .
b1100 *
b1100 /
0#
#155000
b11001100110011001100110011001100 "
b11001100110011001100110011001100 1
b1100 %
b1100 ,
b11001100110011001100110011001100 5
b1100 3
1#
#156000
b11011101110111011101110111011101 8
b1101 7
b1101 +
#160000
b11011101110111011101110111011101 )
b11011101110111011101110111011101 .
b1101 *
b1101 /
0#
#165000
b11011101110111011101110111011101 "
b11011101110111011101110111011101 1
b1101 %
b1101 ,
b11011101110111011101110111011101 5
b1101 3
1#
#166000
b11101110111011101110111011101110 8
b1110 7
b1110 +
#170000
b11101110111011101110111011101110 )
b11101110111011101110111011101110 .
b1110 *
b1110 /
0#
#175000
b11101110111011101110111011101110 "
b11101110111011101110111011101110 1
b1110 %
b1110 ,
b11101110111011101110111011101110 5
b1110 3
1#
#176000
b11111111111111111111111111111111 8
b1111 7
b1111 +
#180000
b11111111111111111111111111111111 )
b11111111111111111111111111111111 .
b1111 *
b1111 /
0#
#185000
b11111111111111111111111111111111 "
b11111111111111111111111111111111 1
b1111 %
b1111 ,
b11111111111111111111111111111111 5
b1111 3
1#
#186000
b10001000100010001000100010000 8
b10000 7
b10000 +
#190000
b10001000100010001000100010000 )
b10001000100010001000100010000 .
b10000 *
b10000 /
0#
#195000
b10001000100010001000100010000 "
b10001000100010001000100010000 1
b10000 %
b10000 ,
b10001000100010001000100010000 5
b10000 3
1#
#196000
b100010001000100010001000100001 8
b10001 7
b10001 +
#200000
b100010001000100010001000100001 )
b100010001000100010001000100001 .
b10001 *
b10001 /
0#
#205000
b100010001000100010001000100001 "
b100010001000100010001000100001 1
b10001 %
b10001 ,
b100010001000100010001000100001 5
b10001 3
1#
#206000
b110011001100110011001100110010 8
b10010 7
b10010 +
#210000
b110011001100110011001100110010 )
b110011001100110011001100110010 .
b10010 *
b10010 /
0#
#215000
b110011001100110011001100110010 "
b110011001100110011001100110010 1
b10010 %
b10010 ,
b110011001100110011001100110010 5
b10010 3
1#
#216000
b1000100010001000100010001000011 8
b10011 7
b10011 +
#220000
b1000100010001000100010001000011 )
b1000100010001000100010001000011 .
b10011 *
b10011 /
0#
#225000
b1000100010001000100010001000011 "
b1000100010001000100010001000011 1
b10011 %
b10011 ,
b1000100010001000100010001000011 5
b10011 3
1#
#226000
b1010101010101010101010101010100 8
b10100 7
b10100 +
#230000
b1010101010101010101010101010100 )
b1010101010101010101010101010100 .
b10100 *
b10100 /
0#
#235000
b1010101010101010101010101010100 "
b1010101010101010101010101010100 1
b10100 %
b10100 ,
b1010101010101010101010101010100 5
b10100 3
1#
#236000
b1100110011001100110011001100101 8
b10101 7
b10101 +
#240000
b1100110011001100110011001100101 )
b1100110011001100110011001100101 .
b10101 *
b10101 /
0#
#245000
b1100110011001100110011001100101 "
b1100110011001100110011001100101 1
b10101 %
b10101 ,
b1100110011001100110011001100101 5
b10101 3
1#
#246000
b1110111011101110111011101110110 8
b10110 7
b10110 +
#250000
b1110111011101110111011101110110 )
b1110111011101110111011101110110 .
b10110 *
b10110 /
0#
#255000
b1110111011101110111011101110110 "
b1110111011101110111011101110110 1
b10110 %
b10110 ,
b1110111011101110111011101110110 5
b10110 3
1#
#256000
b10001000100010001000100010000111 8
b10111 7
b10111 +
#260000
b10001000100010001000100010000111 )
b10001000100010001000100010000111 .
b10111 *
b10111 /
0#
#265000
b10001000100010001000100010000111 "
b10001000100010001000100010000111 1
b10111 %
b10111 ,
b10001000100010001000100010000111 5
b10111 3
1#
#266000
b10011001100110011001100110011000 8
b11000 7
b11000 +
#270000
b10011001100110011001100110011000 )
b10011001100110011001100110011000 .
b11000 *
b11000 /
0#
#275000
b10011001100110011001100110011000 "
b10011001100110011001100110011000 1
b11000 %
b11000 ,
b10011001100110011001100110011000 5
b11000 3
1#
#276000
b10101010101010101010101010101001 8
b11001 7
b11001 +
#280000
b10101010101010101010101010101001 )
b10101010101010101010101010101001 .
b11001 *
b11001 /
0#
#285000
b10101010101010101010101010101001 "
b10101010101010101010101010101001 1
b11001 %
b11001 ,
b10101010101010101010101010101001 5
b11001 3
1#
#286000
b10111011101110111011101110111010 8
b11010 7
b11010 +
#290000
b10111011101110111011101110111010 )
b10111011101110111011101110111010 .
b11010 *
b11010 /
0#
#295000
b10111011101110111011101110111010 "
b10111011101110111011101110111010 1
b11010 %
b11010 ,
b10111011101110111011101110111010 5
b11010 3
1#
#296000
b11001100110011001100110011001011 8
b11011 7
b11011 +
#300000
b11001100110011001100110011001011 )
b11001100110011001100110011001011 .
b11011 *
b11011 /
0#
#305000
b11001100110011001100110011001011 "
b11001100110011001100110011001011 1
b11011 %
b11011 ,
b11001100110011001100110011001011 5
b11011 3
1#
#306000
b11011101110111011101110111011100 8
b11100 7
b11100 +
#310000
b11011101110111011101110111011100 )
b11011101110111011101110111011100 .
b11100 *
b11100 /
0#
#315000
b11011101110111011101110111011100 "
b11011101110111011101110111011100 1
b11100 %
b11100 ,
b11011101110111011101110111011100 5
b11100 3
1#
#316000
b11101110111011101110111011101101 8
b11101 7
b11101 +
#320000
b11101110111011101110111011101101 )
b11101110111011101110111011101101 .
b11101 *
b11101 /
0#
#325000
b11101110111011101110111011101101 "
b11101110111011101110111011101101 1
b11101 %
b11101 ,
b11101110111011101110111011101101 5
b11101 3
1#
#326000
b11111111111111111111111111111110 8
b11110 7
b11110 +
#330000
b11111111111111111111111111111110 )
b11111111111111111111111111111110 .
b11110 *
b11110 /
0#
#335000
b11111111111111111111111111111110 "
b11111111111111111111111111111110 1
b11110 %
b11110 ,
b11111111111111111111111111111110 5
b11110 3
1#
#336000
b10001000100010001000100001111 8
b11111 7
b11111 +
#340000
b10001000100010001000100001111 )
b10001000100010001000100001111 .
b11111 *
b11111 /
0#
#345000
b10001000100010001000100001111 "
b10001000100010001000100001111 1
b11111 %
b11111 ,
b10001000100010001000100001111 5
b11111 3
1#
#346000
b10101010101010100000000000000000 8
b101 7
b100000 +
#350000
b10101010101010100000000000000000 )
b10101010101010100000000000000000 .
b101 *
b101 /
0#
#355000
b1010101010101011111111111111111 8
b1010 7
1#
#360000
b1010101010101011111111111111111 )
b1010101010101011111111111111111 .
b1010 *
b1010 /
0#
#365000
b1010101010101011111111111111111 !
b1010101010101011111111111111111 0
b10101010101010100000000000000000 "
b10101010101010100000000000000000 1
b1010 &
b1010 -
b101 %
b101 ,
b1010101010101011111111111111111 6
b10101010101010100000000000000000 5
b1010 4
b101 3
1#
#366000
b1000000100010010101111010000001 8
b10010 7
b10010 $
b0 +
#370000
b1000000100010010101111010000001 )
b1000000100010010101111010000001 .
b10010 *
b10010 /
0#
#375000
b0 !
b0 0
b1000000100010010101111010000001 "
b1000000100010010101111010000001 1
b0 &
b0 -
b10010 %
b10010 ,
b0 6
b1000000100010010101111010000001 5
b0 4
b10010 3
1#
#376000
b10000110101110010111101100001101 8
b110 7
b110 $
b1 +
#380000
b10000110101110010111101100001101 )
b10000110101110010111101100001101 .
b110 *
b110 /
0#
#385000
b10011001100110011001100110011000 !
b10011001100110011001100110011000 0
b10000110101110010111101100001101 "
b10000110101110010111101100001101 1
b11000 &
b11000 -
b110 %
b110 ,
b10011001100110011001100110011000 6
b10000110101110010111101100001101 5
b11000 4
b110 3
1#
#386000
b1001001101110101001000010010 8
b10 +
#390000
b1001001101110101001000010010 )
b1001001101110101001000010010 .
0#
#395000
b1001001101110101001000010010 "
b1001001101110101001000010010 1
b10001000100010001000100010000 !
b10001000100010001000100010000 0
b10000 &
b10000 -
b10001000100010001000100010000 6
b1001001101110101001000010010 5
b10000 4
1#
#396000
b10111011001000111111000101110110 8
b10000 7
b10000 $
b11 +
#400000
b10111011001000111111000101110110 )
b10111011001000111111000101110110 .
b10000 *
b10000 /
0#
#405000
b1000100010001000100010001000011 !
b1000100010001000100010001000011 0
b10111011001000111111000101110110 "
b10111011001000111111000101110110 1
b10011 &
b10011 -
b10000 %
b10000 ,
b1000100010001000100010001000011 6
b10111011001000111111000101110110 5
b10011 4
b10000 3
1#
#406000
b11000110001011011111011110001100 8
b11110 7
b11110 $
b100 +
#410000
b11000110001011011111011110001100 )
b11000110001011011111011110001100 .
b11110 *
b11110 /
0#
#415000
b10001000100010001000100001111 !
b10001000100010001000100001111 0
b11000110001011011111011110001100 "
b11000110001011011111011110001100 1
b11111 &
b11111 -
b11110 %
b11110 ,
b10001000100010001000100001111 6
b11000110001011011111011110001100 5
b11111 4
b11110 3
1#
#416000
b1100010111101111000010011000101 8
b1100 7
b1100 $
b101 +
#420000
b1100010111101111000010011000101 )
b1100010111101111000010011000101 .
b1100 *
b1100 /
0#
#425000
b1010101010101011111111111111111 !
b1010101010101011111111111111111 0
b1100010111101111000010011000101 "
b1100010111101111000010011000101 1
b1010 &
b1010 -
b1100 %
b1100 ,
b1010101010101011111111111111111 6
b1100010111101111000010011000101 5
b1010 4
b1100 3
1#
#426000
b111011110100100111001001110111 8
b11110 7
b11110 $
b110 +
#430000
b111011110100100111001001110111 )
b111011110100100111001001110111 .
b11110 *
b11110 /
0#
#435000
b10001000100010001000100010001 !
b10001000100010001000100010001 0
b111011110100100111001001110111 "
b111011110100100111001001110111 1
b1 &
b1 -
b11110 %
b11110 ,
b10001000100010001000100010001 6
b111011110100100111001001110111 5
b1 4
b11110 3
1#
#436000
b11111001001100000110100111110010 8
b11000 7
b11000 $
b111 +
#440000
b11111001001100000110100111110010 )
b11111001001100000110100111110010 .
b11000 *
b11000 /
0#
#445000
b1100010111101111000010011000101 !
b1100010111101111000010011000101 0
b11111001001100000110100111110010 "
b11111001001100000110100111110010 1
b1100 &
b1100 -
b11000 %
b11000 ,
b1100010111101111000010011000101 6
b11111001001100000110100111110010 5
b1100 4
b11000 3
1#
#446000
b1100010110010100100111011000101 8
b1110 7
b1110 $
b1000 +
#450000
b1100010110010100100111011000101 )
b1100010110010100100111011000101 .
b1110 *
b1110 /
0#
#455000
b1100110011001100110011001100101 !
b1100110011001100110011001100101 0
b1100010110010100100111011000101 "
b1100010110010100100111011000101 1
b10101 &
b10101 -
b1110 %
b1110 ,
b1100110011001100110011001100101 6
b1100010110010100100111011000101 5
b10101 4
b1110 3
1#
#456000
b10110101010110101100000101101 8
b1011 7
b1011 $
b1001 +
#460000
b10110101010110101100000101101 )
b10110101010110101100000101101 .
b1011 *
b1011 /
0#
#465000
b1001001101110101001000010010 !
b1001001101110101001000010010 0
b10110101010110101100000101101 "
b10110101010110101100000101101 1
b110 &
b110 -
b1011 %
b1011 ,
b1001001101110101001000010010 6
b10110101010110101100000101101 5
b110 4
b1011 3
1#
#466000
b10000101011100111000011100001010 8
b110 7
b110 $
b1010 +
#470000
b10000101011100111000011100001010 )
b10000101011100111000011100001010 .
b110 *
b110 /
0#
#475000
b10001000100010001000100010001000 !
b10001000100010001000100010001000 0
b10000101011100111000011100001010 "
b10000101011100111000011100001010 1
b1000 &
b1000 -
b110 %
b110 ,
b10001000100010001000100010001000 6
b10000101011100111000011100001010 5
b1000 4
b110 3
1#
#476000
b11010101011110000100010110101010 8
b10010 7
b10010 $
b1011 +
#480000
b11010101011110000100010110101010 )
b11010101011110000100010110101010 .
b10010 *
b10010 /
0#
#485000
b10011001100110011001100110011001 !
b10011001100110011001100110011001 0
b11010101011110000100010110101010 "
b11010101011110000100010110101010 1
b1001 &
b1001 -
b10010 %
b10010 ,
b10011001100110011001100110011001 6
b11010101011110000100010110101010 5
b1001 4
b10010 3
1#
#486000
b1001100000111011100000010011 8
b1001 7
b1001 $
b1100 +
#490000
b1001100000111011100000010011 )
b1001100000111011100000010011 .
b1001 *
b1001 /
0#
#495000
b0 !
b0 0
b1001100000111011100000010011 "
b1001100000111011100000010011 1
b0 &
b0 -
b1001 %
b1001 ,
b0 6
b1001100000111011100000010011 5
b0 4
b1001 3
1#
#496000
b10110101100111111101110101101011 8
b101 7
b101 $
b1101 +
#500000
b10110101100111111101110101101011 )
b10110101100111111101110101101011 .
b101 *
b101 /
0#
#505000
b11011101110111011101110111011101 !
b11011101110111011101110111011101 0
b10110101100111111101110101101011 "
b10110101100111111101110101101011 1
b1101 &
b1101 -
b101 %
b101 ,
b11011101110111011101110111011101 6
b10110101100111111101110101101011 5
b1101 4
b101 3
1#
#506000
b0 8
b0 7
b0 $
b1110 +
#510000
b0 )
b0 .
b0 *
b0 /
0#
#515000
b1010101010101011111111111111111 !
b1010101010101011111111111111111 0
b0 "
b0 1
b1010 &
b1010 -
b0 %
b0 ,
b1010101010101011111111111111111 6
b0 5
b1010 4
b0 3
1#
#516000
b1100111110001010111001011001111 8
b10001 7
b10001 $
b1111 +
#520000
b1100111110001010111001011001111 )
b1100111110001010111001011001111 .
b10001 *
b10001 /
0#
#525000
b11010101011110000100010110101010 !
b11010101011110000100010110101010 0
b1100111110001010111001011001111 "
b1100111110001010111001011001111 1
b10010 &
b10010 -
b10001 %
b10001 ,
b11010101011110000100010110101010 6
b1100111110001010111001011001111 5
b10010 4
b10001 3
1#
#526000
b1100101011100110000101011001010 8
b10000 7
b10000 $
b10000 +
#530000
b1100101011100110000101011001010 )
b1100101011100110000101011001010 .
b10000 *
b10000 /
0#
#535000
b110011001100110011001100110011 !
b110011001100110011001100110011 0
b1100101011100110000101011001010 "
b1100101011100110000101011001010 1
b11 &
b11 -
b10000 %
b10000 ,
b110011001100110011001100110011 6
b1100101011100110000101011001010 5
b11 4
b10000 3
1#
#536000
b11000101001011100110000110001010 8
b11111 7
b11111 $
b10001 +
#540000
b11000101001011100110000110001010 )
b11000101001011100110000110001010 .
b11111 *
b11111 /
0#
#545000
b1010101010101010101010101010100 !
b1010101010101010101010101010100 0
b11000101001011100110000110001010 "
b11000101001011100110000110001010 1
b10100 &
b10100 -
b11111 %
b11111 ,
b1010101010101010101010101010100 6
b11000101001011100110000110001010 5
b10100 4
b11111 3
1#
#546000
b10111100001000001111001101111000 8
b1101 7
b1101 $
b10010 +
#550000
b10111100001000001111001101111000 )
b10111100001000001111001101111000 .
b1101 *
b1101 /
0#
#555000
b10001000100010001000100010001000 !
b10001000100010001000100010001000 0
b10111100001000001111001101111000 "
b10111100001000001111001101111000 1
b1000 &
b1000 -
b1101 %
b1101 ,
b10001000100010001000100010001000 6
b10111100001000001111001101111000 5
b1000 4
b1101 3
1#
#556000
b11011011000000100110010110110110 8
b11110 7
b11110 $
b10011 +
#560000
b11011011000000100110010110110110 )
b11011011000000100110010110110110 .
b11110 *
b11110 /
0#
#565000
b11011101110111011101110111011100 !
b11011101110111011101110111011100 0
b11011011000000100110010110110110 "
b11011011000000100110010110110110 1
b11100 &
b11100 -
b11110 %
b11110 ,
b11011101110111011101110111011100 6
b11011011000000100110010110110110 5
b11100 4
b11110 3
1#
#566000
b10100 +
#570000
0#
#571000
1(
#575000
0(
1#
#576000
b10001000100010001000100010001000 !
b10001000100010001000100010001000 0
b0 "
b0 1
b1000 &
b1000 -
b0 %
b0 ,
b10001000100010001000100010001000 6
b0 5
b1000 4
b0 3
b0 +
#577000
b1001100000111011100000010011 !
b1001100000111011100000010011 0
b10001000100010001000100010001 "
b10001000100010001000100010001 1
b1001 &
b1001 -
b1 %
b1 ,
b1001100000111011100000010011 6
b10001000100010001000100010001 5
b1001 4
b1 3
b1 +
#578000
b1010101010101011111111111111111 !
b1010101010101011111111111111111 0
b100010001000100010001000100010 "
b100010001000100010001000100010 1
b1010 &
b1010 -
b10 %
b10 ,
b1010101010101011111111111111111 6
b100010001000100010001000100010 5
b1010 4
b10 3
b10 +
#579000
b10110101010110101100000101101 !
b10110101010110101100000101101 0
b110011001100110011001100110011 "
b110011001100110011001100110011 1
b1011 &
b1011 -
b11 %
b11 ,
b10110101010110101100000101101 6
b110011001100110011001100110011 5
b1011 4
b11 3
b11 +
#580000
b1100010111101111000010011000101 !
b1100010111101111000010011000101 0
b1000100010001000100010001000100 "
b1000100010001000100010001000100 1
b1100 &
b1100 -
b100 %
b100 ,
b1100010111101111000010011000101 6
b1000100010001000100010001000100 5
b1100 4
b100 3
b100 +
0#
#581000
b10111100001000001111001101111000 !
b10111100001000001111001101111000 0
b10110101100111111101110101101011 "
b10110101100111111101110101101011 1
b1101 &
b1101 -
b101 %
b101 ,
b10111100001000001111001101111000 6
b10110101100111111101110101101011 5
b1101 4
b101 3
b101 +
#582000
b1100010110010100100111011000101 !
b1100010110010100100111011000101 0
b10000101011100111000011100001010 "
b10000101011100111000011100001010 1
b1110 &
b1110 -
b110 %
b110 ,
b1100010110010100100111011000101 6
b10000101011100111000011100001010 5
b1110 4
b110 3
b110 +
#583000
b11111111111111111111111111111111 !
b11111111111111111111111111111111 0
b1110111011101110111011101110111 "
b1110111011101110111011101110111 1
b1111 &
b1111 -
b111 %
b111 ,
b11111111111111111111111111111111 6
b1110111011101110111011101110111 5
b1111 4
b111 3
b111 +
#584000
b1000 +
