include/defines.vh
`define DATA_WIDTH 32
`define ADDR_WIDTH 11  

// Immediate Src
`define Imm_I 3'b000 
`define Imm_S 3'b001 
`define Imm_B 3'b010 
`define Imm_U 3'b011 
`define Imm_J 3'b100 
`define Imm_NONE 3'b111

// ALU Operations
`define ALU_ADD 4'b0000
`define ALU_SUB 4'b0001
`define ALU_SLL 4'b0010
`define ALU_SLT 4'b0011
`define ALU_SLTU 4'b0100
`define ALU_XOR 4'b0101
`define ALU_SRL 4'b0110
`define ALU_SRA 4'b0111
`define ALU_OR 4'b1000
`define ALU_AND 4'b1001
`define ALU_LUI 4'b1010

// Control Signals
`define OP_RTYPE 7'b0110011
`define OP_ITYPE 7'b0010011
`define OP_LOAD 7'b0000011
`define OP_STORE 7'b0100011
`define OP_BRANCH 7'b1100011
`define OP_JAL 7'b1101111
`define OP_JALR 7'b1100111
`define OP_LUI 7'b0110111
`define OP_AUIPC 7'b0010111
`define OP_SYSTEM 7'b1110011

src/leaf/wb_mux.v
`timescale 1ps / 1ps
`include "defines.vh"

// wb_sel encodings
localparam WB_ALU = 2'd0;
localparam WB_MEM = 2'd1;
localparam WB_PC4 = 2'd2;

module wb_mux (
    input wire [`DATA_WIDTH-1:0] alu_result,
    input wire [`DATA_WIDTH-1:0] rdata,         // data from data_mem (already extended)
    input wire [`DATA_WIDTH-1:0] pc_plus4,
    input wire [            1:0] wb_sel,        // WB_ALU/MEM/PC4
    input wire                   reg_write_in,  // from control
    input wire                   kill_wb,       // from trap/exception unit
    input wire [            4:0] rd_in,         // destination register index

    output reg  [`DATA_WIDTH-1:0] rd_wdata,
    output wire                   reg_write_out,  // gated write-enable
    output wire [            4:0] rd_out
);

  always @* begin
    case (wb_sel)
      WB_ALU:  rd_wdata = alu_result;
      WB_MEM:  rd_wdata = rdata;
      WB_PC4:  rd_wdata = pc_plus4;
      default: rd_wdata = {`DATA_WIDTH{1'b0}};
    endcase
  end

  // Block writes on kill, and avoid x0 writes here (regfile also ignores)
  assign reg_write_out = reg_write_in && !kill_wb && (rd_in != 5'd0);
  assign rd_out        = rd_in;

endmodule

tb/wb_mux_tb.v
`timescale 1ps / 1ps
`include "defines.vh"

module wb_mux_tb;
  localparam [1:0] WB_ALU = 2'd0, WB_MEM = 2'd1, WB_PC4 = 2'd2;

  reg [`DATA_WIDTH-1:0] alu_result, rdata, pc_plus4;
  reg [1:0] wb_sel;
  reg reg_write_in, kill_wb;
  reg  [            4:0] rd_in;

  wire [`DATA_WIDTH-1:0] rd_wdata;
  wire                   reg_write_out;
  wire [            4:0] rd_out;

  wb_mux dut (
      .alu_result(alu_result),
      .rdata(rdata),
      .pc_plus4(pc_plus4),
      .wb_sel(wb_sel),
      .reg_write_in(reg_write_in),
      .kill_wb(kill_wb),
      .rd_in(rd_in),
      .rd_wdata(rd_wdata),
      .reg_write_out(reg_write_out),
      .rd_out(rd_out)
  );

  integer fails;

  initial begin
    fails        = 0;
    alu_result   = 32'hA1A1_A1A1;
    rdata        = 32'hB2B2_B2B2;
    pc_plus4     = 32'hC3C3_C3C3;
    reg_write_in = 1'b1;
    kill_wb      = 1'b0;
    rd_in        = 5'd10;

    wb_sel       = WB_ALU;
    #1;
    check("ALU path data", rd_wdata === alu_result);
    check("ALU path reg_write", reg_write_out === 1'b1);
    check("ALU rd passthrough", rd_out === rd_in);

    wb_sel = WB_MEM;
    #1;
    check("MEM path data", rd_wdata === rdata);

    wb_sel = WB_PC4;
    #1;
    check("PC+4 path data", rd_wdata === pc_plus4);

    kill_wb = 1'b1;
    #1;
    check("Kill gating disables write", reg_write_out === 1'b0);
    kill_wb = 1'b0;
    #1;

    rd_in  = 5'd0;
    wb_sel = WB_ALU;
    #1;
    check("x0 write blocked", reg_write_out === 1'b0);
    rd_in = 5'd31;
    #1;
    check("x31 write allowed", reg_write_out === 1'b1);

    if (fails == 0) $display("PASS: all wb_mux tests");
    else $display("FAIL: %0d test(s)", fails);
    $finish;
  end

  task check;
    input [8*64-1:0] name;
    input cond;
    begin
      if (!cond) begin
        $display("FAIL: %0s", name);
        fails = fails + 1;
      end else begin
        $display("PASS: %0s", name);
      end
    end
  endtask
endmodule

waves/wb_mux.vcd
$date
	Tue Aug 26 21:19:24 2025
$end
$version
	Icarus Verilog
$end
$timescale
	1ps
$end
$scope module wb_mux_tb $end
$var wire 1 ! reg_write_out $end
$var wire 32 " rd_wdata [31:0] $end
$var wire 5 # rd_out [4:0] $end
$var parameter 2 $ WB_ALU $end
$var parameter 2 % WB_MEM $end
$var parameter 2 & WB_PC4 $end
$var reg 32 ' alu_result [31:0] $end
$var reg 1 ( kill_wb $end
$var reg 32 ) pc_plus4 [31:0] $end
$var reg 5 * rd_in [4:0] $end
$var reg 32 + rdata [31:0] $end
$var reg 1 , reg_write_in $end
$var reg 2 - wb_sel [1:0] $end
$var integer 32 . fails [31:0] $end
$scope module dut $end
$var wire 32 / alu_result [31:0] $end
$var wire 1 ( kill_wb $end
$var wire 32 0 pc_plus4 [31:0] $end
$var wire 5 1 rd_in [4:0] $end
$var wire 5 2 rd_out [4:0] $end
$var wire 32 3 rdata [31:0] $end
$var wire 1 , reg_write_in $end
$var wire 1 ! reg_write_out $end
$var wire 2 4 wb_sel [1:0] $end
$var parameter 2 5 WB_ALU $end
$var parameter 2 6 WB_MEM $end
$var parameter 2 7 WB_PC4 $end
$var reg 32 8 rd_wdata [31:0] $end
$upscope $end
$scope task check $end
$var reg 1 9 cond $end
$var reg 512 : name [511:0] $end
$upscope $end
$upscope $end
$enddefinitions $end
$comment Show the parameter values. $end
$dumpall
b10 7
b1 6
b0 5
b10 &
b1 %
b0 $
$end
#0
$dumpvars
bx :
x9
b10100001101000011010000110100001 8
b0 4
b10110010101100101011001010110010 3
b1010 2
b1010 1
b11000011110000111100001111000011 0
b10100001101000011010000110100001 /
b0 .
b0 -
1,
b10110010101100101011001010110010 +
b1010 *
b11000011110000111100001111000011 )
0(
b10100001101000011010000110100001 '
b1010 #
b10100001101000011010000110100001 "
1!
$end
#1
b10110010101100101011001010110010 "
b10110010101100101011001010110010 8
b1 -
b1 4
19
b10000010100110001010101001000000111001001100100001000000111000001100001011100110111001101110100011010000111001001101111011101010110011101101000 :
#2
b11000011110000111100001111000011 "
b11000011110000111100001111000011 8
b10 -
b10 4
b1001101010001010100110100100000011100000110000101110100011010000010000001100100011000010111010001100001 :
#3
0!
1(
b101000001000011001010110011010000100000011100000110000101110100011010000010000001100100011000010111010001100001 :
#4
1!
0(
b100101101101001011011000110110000100000011001110110000101110100011010010110111001100111001000000110010001101001011100110110000101100010011011000110010101110011001000000111011101110010011010010111010001100101 :
#5
b10100001101000011010000110100001 "
b10100001101000011010000110100001 8
0!
b0 -
b0 4
b0 #
b0 2
b0 *
b0 1
#6
1!
b11111 #
b11111 2
b11111 *
b11111 1
b1111000001100000010000001110111011100100110100101110100011001010010000001100010011011000110111101100011011010110110010101100100 :
#7
b111100000110011001100010010000001110111011100100110100101110100011001010010000001100001011011000110110001101111011101110110010101100100 :
